<mesh>
	<sharedgeometry vertexcount="468">
		<vertexbuffer positions="true" normals="true" colours_diffuse="false" texture_coords="1" texture_coords_dimensions_0="2">
			<vertex>
				<position x="-0.0619189" y="-0.0208716" z="0.0142512"/>
				<normal x="-0.999296" y="-0.0373319" z="0.003683"/>
				<texcoord u="0.00455592" v="0.167526"/>
			</vertex>
			<vertex>
				<position x="-0.0619189" y="-0.0101829" z="0.0936022"/>
				<normal x="-0.838996" y="0.0330366" z="0.543133"/>
				<texcoord u="0.00455592" v="0.0845604"/>
			</vertex>
			<vertex>
				<position x="-0.0728463" y="0.275061" z="0.049006"/>
				<normal x="-0.878405" y="0.0223251" z="0.477395"/>
				<texcoord u="0.343083" v="0.0845604"/>
			</vertex>
			<vertex>
				<position x="-0.0728463" y="0.275061" z="0.049006"/>
				<normal x="-0.878405" y="0.0223251" z="0.477395"/>
				<texcoord u="0.343083" v="0.0845604"/>
			</vertex>
			<vertex>
				<position x="-0.0722523" y="0.264689" z="-0.0360884"/>
				<normal x="-0.981095" y="-0.0850404" z="-0.17384"/>
				<texcoord u="0.343083" v="0.167526"/>
			</vertex>
			<vertex>
				<position x="-0.0619189" y="-0.0208716" z="0.0142512"/>
				<normal x="-0.999296" y="-0.0373319" z="0.003683"/>
				<texcoord u="0.00455592" v="0.167526"/>
			</vertex>
			<vertex>
				<position x="-0.0619189" y="-0.0101829" z="0.0936022"/>
				<normal x="-0.838996" y="0.0330366" z="0.543133"/>
				<texcoord u="0.00455592" v="0.0845604"/>
			</vertex>
			<vertex>
				<position x="-0.00282273" y="-0.00927247" z="0.121535"/>
				<normal x="-0.0120503" y="0.0943222" z="0.995469"/>
				<texcoord u="0.00455592" v="0.00538731"/>
			</vertex>
			<vertex>
				<position x="-0.00285787" y="0.282101" z="0.0939267"/>
				<normal x="-0.00729837" y="0.106462" z="0.99429"/>
				<texcoord u="0.343083" v="0.00538731"/>
			</vertex>
			<vertex>
				<position x="-0.00285787" y="0.282101" z="0.0939267"/>
				<normal x="-0.00729837" y="0.106462" z="0.99429"/>
				<texcoord u="0.343083" v="0.00538731"/>
			</vertex>
			<vertex>
				<position x="-0.0728463" y="0.275061" z="0.049006"/>
				<normal x="-0.878405" y="0.0223251" z="0.477395"/>
				<texcoord u="0.343083" v="0.0845604"/>
			</vertex>
			<vertex>
				<position x="-0.0619189" y="-0.0101829" z="0.0936022"/>
				<normal x="-0.838996" y="0.0330366" z="0.543133"/>
				<texcoord u="0.00455592" v="0.0845604"/>
			</vertex>
			<vertex>
				<position x="-0.00285787" y="0.282101" z="0.0939267"/>
				<normal x="-0.00729837" y="0.106462" z="0.99429"/>
				<texcoord u="0.343083" v="0.00538731"/>
			</vertex>
			<vertex>
				<position x="-0.00282273" y="-0.00927247" z="0.121535"/>
				<normal x="-0.0120503" y="0.0943222" z="0.995469"/>
				<texcoord u="0.00455592" v="0.00538731"/>
			</vertex>
			<vertex>
				<position x="0.0602429" y="-0.0101829" z="0.0936022"/>
				<normal x="0.835434" y="0.0429829" z="0.547907"/>
				<texcoord u="0.00455592" v="0.0845604"/>
			</vertex>
			<vertex>
				<position x="0.0602429" y="-0.0101829" z="0.0936022"/>
				<normal x="0.835434" y="0.0429829" z="0.547907"/>
				<texcoord u="0.00455592" v="0.0845604"/>
			</vertex>
			<vertex>
				<position x="0.0672009" y="0.275061" z="0.049006"/>
				<normal x="0.880529" y="0.0182263" z="0.473642"/>
				<texcoord u="0.343083" v="0.0845604"/>
			</vertex>
			<vertex>
				<position x="-0.00285787" y="0.282101" z="0.0939267"/>
				<normal x="-0.00729837" y="0.106462" z="0.99429"/>
				<texcoord u="0.343083" v="0.00538731"/>
			</vertex>
			<vertex>
				<position x="0.0602429" y="-0.0101829" z="0.0936022"/>
				<normal x="0.835434" y="0.0429829" z="0.547907"/>
				<texcoord u="0.00455592" v="0.0845604"/>
			</vertex>
			<vertex>
				<position x="0.0602429" y="-0.0208716" z="0.0142512"/>
				<normal x="0.999759" y="-0.0217657" z="0.00293187"/>
				<texcoord u="0.00455592" v="0.167526"/>
			</vertex>
			<vertex>
				<position x="0.0666086" y="0.26474" z="-0.036098"/>
				<normal x="0.981646" y="-0.0801312" z="-0.173061"/>
				<texcoord u="0.343083" v="0.167526"/>
			</vertex>
			<vertex>
				<position x="0.0666086" y="0.26474" z="-0.036098"/>
				<normal x="0.981646" y="-0.0801312" z="-0.173061"/>
				<texcoord u="0.343083" v="0.167526"/>
			</vertex>
			<vertex>
				<position x="0.0672009" y="0.275061" z="0.049006"/>
				<normal x="0.880529" y="0.0182263" z="0.473642"/>
				<texcoord u="0.343083" v="0.0845604"/>
			</vertex>
			<vertex>
				<position x="0.0602429" y="-0.0101829" z="0.0936022"/>
				<normal x="0.835434" y="0.0429829" z="0.547907"/>
				<texcoord u="0.00455592" v="0.0845604"/>
			</vertex>
			<vertex>
				<position x="-0.00250604" y="0.650644" z="-0.15664"/>
				<normal x="0.000539171" y="-0.260802" z="-0.965392"/>
				<texcoord u="0.767298" v="0.24109"/>
			</vertex>
			<vertex>
				<position x="-0.102504" y="0.660101" z="-0.0982915"/>
				<normal x="-0.854534" y="-0.211286" z="-0.474478"/>
				<texcoord u="0.767298" v="0.167526"/>
			</vertex>
			<vertex>
				<position x="-0.14912" y="0.871484" z="-0.136714"/>
				<normal x="-0.865528" y="-0.268123" z="-0.423049"/>
				<texcoord u="0.995449" v="0.167526"/>
			</vertex>
			<vertex>
				<position x="-0.14912" y="0.871484" z="-0.136714"/>
				<normal x="-0.865528" y="-0.268123" z="-0.423049"/>
				<texcoord u="0.995449" v="0.167526"/>
			</vertex>
			<vertex>
				<position x="-0.00263746" y="0.856917" z="-0.222936"/>
				<normal x="-0.000612257" y="-0.305983" z="-0.952037"/>
				<texcoord u="0.995449" v="0.24109"/>
			</vertex>
			<vertex>
				<position x="-0.00250604" y="0.650644" z="-0.15664"/>
				<normal x="0.000539171" y="-0.260802" z="-0.965392"/>
				<texcoord u="0.767298" v="0.24109"/>
			</vertex>
			<vertex>
				<position x="-0.14912" y="0.871484" z="-0.136714"/>
				<normal x="-0.865528" y="-0.268123" z="-0.423049"/>
				<texcoord u="0.995449" v="0.167526"/>
			</vertex>
			<vertex>
				<position x="-0.102504" y="0.660101" z="-0.0982915"/>
				<normal x="-0.854534" y="-0.211286" z="-0.474478"/>
				<texcoord u="0.767298" v="0.167526"/>
			</vertex>
			<vertex>
				<position x="-0.102801" y="0.677552" z="0.00508246"/>
				<normal x="-0.832539" y="-0.0912095" z="0.546405"/>
				<texcoord u="0.767298" v="0.0845604"/>
			</vertex>
			<vertex>
				<position x="-0.102801" y="0.677552" z="0.00508246"/>
				<normal x="-0.832539" y="-0.0912095" z="0.546405"/>
				<texcoord u="0.767298" v="0.0845604"/>
			</vertex>
			<vertex>
				<position x="-0.14912" y="0.894747" z="0.000976083"/>
				<normal x="-0.819603" y="-0.164412" z="0.548835"/>
				<texcoord u="0.995449" v="0.0845604"/>
			</vertex>
			<vertex>
				<position x="-0.14912" y="0.871484" z="-0.136714"/>
				<normal x="-0.865528" y="-0.268123" z="-0.423049"/>
				<texcoord u="0.995449" v="0.167526"/>
			</vertex>
			<vertex>
				<position x="-0.102801" y="0.677552" z="0.00508246"/>
				<normal x="-0.832539" y="-0.0912095" z="0.546405"/>
				<texcoord u="0.767298" v="0.0845604"/>
			</vertex>
			<vertex>
				<position x="-0.00195272" y="0.692634" z="0.0518426"/>
				<normal x="0.00241668" y="-0.00879112" z="0.999958"/>
				<texcoord u="0.783929" v="0.00538731"/>
			</vertex>
			<vertex>
				<position x="-0.00266526" y="0.906791" z="0.0722652"/>
				<normal x="0.00194155" y="-0.0902665" z="0.995916"/>
				<texcoord u="0.995449" v="0.00538731"/>
			</vertex>
			<vertex>
				<position x="-0.00266526" y="0.906791" z="0.0722652"/>
				<normal x="0.00194155" y="-0.0902665" z="0.995916"/>
				<texcoord u="0.995449" v="0.00538731"/>
			</vertex>
			<vertex>
				<position x="-0.14912" y="0.894747" z="0.000976083"/>
				<normal x="-0.819603" y="-0.164412" z="0.548835"/>
				<texcoord u="0.995449" v="0.0845604"/>
			</vertex>
			<vertex>
				<position x="-0.102801" y="0.677552" z="0.00508246"/>
				<normal x="-0.832539" y="-0.0912095" z="0.546405"/>
				<texcoord u="0.767298" v="0.0845604"/>
			</vertex>
			<vertex>
				<position x="-0.00195272" y="0.692634" z="0.0518426"/>
				<normal x="0.00241668" y="-0.00879112" z="0.999958"/>
				<texcoord u="0.783929" v="0.00538731"/>
			</vertex>
			<vertex>
				<position x="0.0974738" y="0.677552" z="0.00508245"/>
				<normal x="0.836015" y="-0.082912" z="0.542407"/>
				<texcoord u="0.767298" v="0.0845604"/>
			</vertex>
			<vertex>
				<position x="0.144148" y="0.894747" z="0.000976059"/>
				<normal x="0.817241" y="-0.168841" z="0.551007"/>
				<texcoord u="0.995449" v="0.0845604"/>
			</vertex>
			<vertex>
				<position x="0.144148" y="0.894747" z="0.000976059"/>
				<normal x="0.817241" y="-0.168841" z="0.551007"/>
				<texcoord u="0.995449" v="0.0845604"/>
			</vertex>
			<vertex>
				<position x="-0.00266526" y="0.906791" z="0.0722652"/>
				<normal x="0.00194155" y="-0.0902665" z="0.995916"/>
				<texcoord u="0.995449" v="0.00538731"/>
			</vertex>
			<vertex>
				<position x="-0.00195272" y="0.692634" z="0.0518426"/>
				<normal x="0.00241668" y="-0.00879112" z="0.999958"/>
				<texcoord u="0.783929" v="0.00538731"/>
			</vertex>
			<vertex>
				<position x="0.144148" y="0.871484" z="-0.136714"/>
				<normal x="0.865417" y="-0.269026" z="-0.422704"/>
				<texcoord u="0.995449" v="0.167526"/>
			</vertex>
			<vertex>
				<position x="0.144148" y="0.894747" z="0.000976059"/>
				<normal x="0.817241" y="-0.168841" z="0.551007"/>
				<texcoord u="0.995449" v="0.0845604"/>
			</vertex>
			<vertex>
				<position x="0.0974738" y="0.677552" z="0.00508245"/>
				<normal x="0.836015" y="-0.082912" z="0.542407"/>
				<texcoord u="0.767298" v="0.0845604"/>
			</vertex>
			<vertex>
				<position x="0.0974738" y="0.677552" z="0.00508245"/>
				<normal x="0.836015" y="-0.082912" z="0.542407"/>
				<texcoord u="0.767298" v="0.0845604"/>
			</vertex>
			<vertex>
				<position x="0.0971776" y="0.660101" z="-0.098292"/>
				<normal x="0.854777" y="-0.212136" z="-0.473661"/>
				<texcoord u="0.767298" v="0.167526"/>
			</vertex>
			<vertex>
				<position x="0.144148" y="0.871484" z="-0.136714"/>
				<normal x="0.865417" y="-0.269026" z="-0.422704"/>
				<texcoord u="0.995449" v="0.167526"/>
			</vertex>
			<vertex>
				<position x="0.144148" y="0.871484" z="-0.136714"/>
				<normal x="0.865417" y="-0.269026" z="-0.422704"/>
				<texcoord u="0.995449" v="0.167526"/>
			</vertex>
			<vertex>
				<position x="0.0971776" y="0.660101" z="-0.098292"/>
				<normal x="0.854777" y="-0.212136" z="-0.473661"/>
				<texcoord u="0.767298" v="0.167526"/>
			</vertex>
			<vertex>
				<position x="-0.00250604" y="0.650644" z="-0.15664"/>
				<normal x="0.000539171" y="-0.260802" z="-0.965392"/>
				<texcoord u="0.767298" v="0.24109"/>
			</vertex>
			<vertex>
				<position x="-0.00250604" y="0.650644" z="-0.15664"/>
				<normal x="0.000539171" y="-0.260802" z="-0.965392"/>
				<texcoord u="0.767298" v="0.24109"/>
			</vertex>
			<vertex>
				<position x="-0.00263746" y="0.856917" z="-0.222936"/>
				<normal x="-0.000612257" y="-0.305983" z="-0.952037"/>
				<texcoord u="0.995449" v="0.24109"/>
			</vertex>
			<vertex>
				<position x="0.144148" y="0.871484" z="-0.136714"/>
				<normal x="0.865417" y="-0.269026" z="-0.422704"/>
				<texcoord u="0.995449" v="0.167526"/>
			</vertex>
			<vertex>
				<position x="-0.00266526" y="0.906791" z="0.0722652"/>
				<normal x="1.3822e-007" y="0.986027" z="-0.166588"/>
				<texcoord u="0.0557277" v="0.174998"/>
			</vertex>
			<vertex>
				<position x="0.144148" y="0.894747" z="0.000976059"/>
				<normal x="-4.47984e-008" y="0.986027" z="-0.166588"/>
				<texcoord u="0.159741" v="0.174998"/>
			</vertex>
			<vertex>
				<position x="0.0877349" y="0.88857" z="-0.0355812"/>
				<normal x="1.08279e-007" y="0.986027" z="-0.166588"/>
				<texcoord u="0.142406" v="0.20329"/>
			</vertex>
			<vertex>
				<position x="0.0877349" y="0.88857" z="-0.0355812"/>
				<normal x="1.08279e-007" y="0.986027" z="-0.166588"/>
				<texcoord u="0.142406" v="0.20329"/>
			</vertex>
			<vertex>
				<position x="-0.00266525" y="0.896121" z="0.00910949"/>
				<normal x="3.88336e-007" y="0.986027" z="-0.166588"/>
				<texcoord u="0.0730633" v="0.20329"/>
			</vertex>
			<vertex>
				<position x="-0.00266526" y="0.906791" z="0.0722652"/>
				<normal x="1.3822e-007" y="0.986027" z="-0.166588"/>
				<texcoord u="0.0557277" v="0.174998"/>
			</vertex>
			<vertex>
				<position x="0.0877349" y="0.88857" z="-0.0355812"/>
				<normal x="-0.801495" y="0.27188" z="-0.532623"/>
				<texcoord u="0.142406" v="0.20329"/>
			</vertex>
			<vertex>
				<position x="-0.00266546" y="0.611711" z="-0.0408701"/>
				<normal x="-0.00612917" y="0.991373" z="-0.130925"/>
				<texcoord u="0.109712" v="0.268158"/>
			</vertex>
			<vertex>
				<position x="-0.00266525" y="0.896121" z="0.00910949"/>
				<normal x="-0.00893167" y="0.173072" z="-0.984869"/>
				<texcoord u="0.0730633" v="0.20329"/>
			</vertex>
			<vertex>
				<position x="-0.00263746" y="0.856917" z="-0.222936"/>
				<normal x="1.15318e-007" y="0.986027" z="-0.166588"/>
				<texcoord u="0.159741" v="0.174998"/>
			</vertex>
			<vertex>
				<position x="-0.14912" y="0.871484" z="-0.136714"/>
				<normal x="-8.0375e-008" y="0.986027" z="-0.166588"/>
				<texcoord u="0.0557277" v="0.174998"/>
			</vertex>
			<vertex>
				<position x="-0.0903249" y="0.874064" z="-0.121446"/>
				<normal x="1.6469e-007" y="0.986027" z="-0.166588"/>
				<texcoord u="0.0730633" v="0.20329"/>
			</vertex>
			<vertex>
				<position x="-0.0903249" y="0.874064" z="-0.121446"/>
				<normal x="1.6469e-007" y="0.986027" z="-0.166588"/>
				<texcoord u="0.0730633" v="0.20329"/>
			</vertex>
			<vertex>
				<position x="-0.00263747" y="0.86706" z="-0.162903"/>
				<normal x="3.29818e-007" y="0.986027" z="-0.166588"/>
				<texcoord u="0.142406" v="0.20329"/>
			</vertex>
			<vertex>
				<position x="-0.00263746" y="0.856917" z="-0.222936"/>
				<normal x="1.15318e-007" y="0.986027" z="-0.166588"/>
				<texcoord u="0.159741" v="0.174998"/>
			</vertex>
			<vertex>
				<position x="-0.0903249" y="0.874064" z="-0.121446"/>
				<normal x="0.795522" y="0.404393" z="0.451232"/>
				<texcoord u="0.0730633" v="0.20329"/>
			</vertex>
			<vertex>
				<position x="-0.0954387" y="0.888768" z="-0.0344137"/>
				<normal x="0.802276" y="0.280919" z="-0.526724"/>
				<texcoord u="0.0403032" v="0.268158"/>
			</vertex>
			<vertex>
				<position x="-0.00266546" y="0.611711" z="-0.0408701"/>
				<normal x="-0.00612917" y="0.991373" z="-0.130925"/>
				<texcoord u="0.109712" v="0.268158"/>
			</vertex>
			<vertex>
				<position x="-0.00263746" y="0.856917" z="-0.222936"/>
				<normal x="1.15318e-007" y="0.986027" z="-0.166588"/>
				<texcoord u="0.159741" v="0.174998"/>
			</vertex>
			<vertex>
				<position x="-0.00263747" y="0.86706" z="-0.162903"/>
				<normal x="3.29818e-007" y="0.986027" z="-0.166588"/>
				<texcoord u="0.142406" v="0.20329"/>
			</vertex>
			<vertex>
				<position x="0.0860969" y="0.876037" z="-0.109769"/>
				<normal x="-4.10116e-007" y="0.986027" z="-0.166587"/>
				<texcoord u="0.179121" v="0.268158"/>
			</vertex>
			<vertex>
				<position x="0.0860969" y="0.876037" z="-0.109769"/>
				<normal x="-4.10116e-007" y="0.986027" z="-0.166587"/>
				<texcoord u="0.179121" v="0.268158"/>
			</vertex>
			<vertex>
				<position x="0.144148" y="0.871484" z="-0.136714"/>
				<normal x="-6.53654e-007" y="0.986027" z="-0.166587"/>
				<texcoord u="0.210355" v="0.268158"/>
			</vertex>
			<vertex>
				<position x="-0.00263746" y="0.856917" z="-0.222936"/>
				<normal x="1.15318e-007" y="0.986027" z="-0.166588"/>
				<texcoord u="0.159741" v="0.174998"/>
			</vertex>
			<vertex>
				<position x="0.144148" y="0.894747" z="0.000976059"/>
				<normal x="-4.47984e-008" y="0.986027" z="-0.166588"/>
				<texcoord u="0.159741" v="0.174998"/>
			</vertex>
			<vertex>
				<position x="0.144148" y="0.871484" z="-0.136714"/>
				<normal x="-6.53654e-007" y="0.986027" z="-0.166587"/>
				<texcoord u="0.210355" v="0.268158"/>
			</vertex>
			<vertex>
				<position x="0.0860969" y="0.876037" z="-0.109769"/>
				<normal x="-4.10116e-007" y="0.986027" z="-0.166587"/>
				<texcoord u="0.179121" v="0.268158"/>
			</vertex>
			<vertex>
				<position x="0.0860969" y="0.876037" z="-0.109769"/>
				<normal x="-4.10116e-007" y="0.986027" z="-0.166587"/>
				<texcoord u="0.179121" v="0.268158"/>
			</vertex>
			<vertex>
				<position x="0.0877349" y="0.88857" z="-0.0355812"/>
				<normal x="1.08279e-007" y="0.986027" z="-0.166588"/>
				<texcoord u="0.142406" v="0.20329"/>
			</vertex>
			<vertex>
				<position x="0.144148" y="0.894747" z="0.000976059"/>
				<normal x="-4.47984e-008" y="0.986027" z="-0.166588"/>
				<texcoord u="0.159741" v="0.174998"/>
			</vertex>
			<vertex>
				<position x="-0.00266526" y="0.906791" z="0.0722652"/>
				<normal x="1.3822e-007" y="0.986027" z="-0.166588"/>
				<texcoord u="0.0557277" v="0.174998"/>
			</vertex>
			<vertex>
				<position x="-0.00266525" y="0.896121" z="0.00910949"/>
				<normal x="3.88336e-007" y="0.986027" z="-0.166588"/>
				<texcoord u="0.0730633" v="0.20329"/>
			</vertex>
			<vertex>
				<position x="-0.0954387" y="0.888768" z="-0.0344137"/>
				<normal x="-6.66612e-007" y="0.986027" z="-0.166587"/>
				<texcoord u="0.0403032" v="0.268158"/>
			</vertex>
			<vertex>
				<position x="-0.0954387" y="0.888768" z="-0.0344137"/>
				<normal x="-6.66612e-007" y="0.986027" z="-0.166587"/>
				<texcoord u="0.0403032" v="0.268158"/>
			</vertex>
			<vertex>
				<position x="-0.14912" y="0.894747" z="0.000976083"/>
				<normal x="-1.00088e-006" y="0.986027" z="-0.166587"/>
				<texcoord u="0.00559882" v="0.268158"/>
			</vertex>
			<vertex>
				<position x="-0.00266526" y="0.906791" z="0.0722652"/>
				<normal x="1.3822e-007" y="0.986027" z="-0.166588"/>
				<texcoord u="0.0557277" v="0.174998"/>
			</vertex>
			<vertex>
				<position x="-0.14912" y="0.871484" z="-0.136714"/>
				<normal x="-8.0375e-008" y="0.986027" z="-0.166588"/>
				<texcoord u="0.0557277" v="0.174998"/>
			</vertex>
			<vertex>
				<position x="-0.14912" y="0.894747" z="0.000976083"/>
				<normal x="-1.00088e-006" y="0.986027" z="-0.166587"/>
				<texcoord u="0.00559882" v="0.268158"/>
			</vertex>
			<vertex>
				<position x="-0.0954387" y="0.888768" z="-0.0344137"/>
				<normal x="-6.66612e-007" y="0.986027" z="-0.166587"/>
				<texcoord u="0.0403032" v="0.268158"/>
			</vertex>
			<vertex>
				<position x="-0.0954387" y="0.888768" z="-0.0344137"/>
				<normal x="-6.66612e-007" y="0.986027" z="-0.166587"/>
				<texcoord u="0.0403032" v="0.268158"/>
			</vertex>
			<vertex>
				<position x="-0.0903249" y="0.874064" z="-0.121446"/>
				<normal x="1.6469e-007" y="0.986027" z="-0.166588"/>
				<texcoord u="0.0730633" v="0.20329"/>
			</vertex>
			<vertex>
				<position x="-0.14912" y="0.871484" z="-0.136714"/>
				<normal x="-8.0375e-008" y="0.986027" z="-0.166588"/>
				<texcoord u="0.0557277" v="0.174998"/>
			</vertex>
			<vertex>
				<position x="0.0860969" y="0.876037" z="-0.109769"/>
				<normal x="-0.833241" y="0.383601" z="0.398196"/>
				<texcoord u="0.179121" v="0.268158"/>
			</vertex>
			<vertex>
				<position x="-0.00263747" y="0.86706" z="-0.162903"/>
				<normal x="-0.0439229" y="0.430784" z="0.901385"/>
				<texcoord u="0.142406" v="0.20329"/>
			</vertex>
			<vertex>
				<position x="-0.00266546" y="0.611711" z="-0.0408701"/>
				<normal x="-0.00612917" y="0.991373" z="-0.130925"/>
				<texcoord u="0.109712" v="0.268158"/>
			</vertex>
			<vertex>
				<position x="-0.00266546" y="0.611711" z="-0.0408701"/>
				<normal x="-0.00612917" y="0.991373" z="-0.130925"/>
				<texcoord u="0.109712" v="0.268158"/>
			</vertex>
			<vertex>
				<position x="-0.00263747" y="0.86706" z="-0.162903"/>
				<normal x="-0.0439229" y="0.430784" z="0.901385"/>
				<texcoord u="0.142406" v="0.20329"/>
			</vertex>
			<vertex>
				<position x="-0.0903249" y="0.874064" z="-0.121446"/>
				<normal x="0.795522" y="0.404393" z="0.451232"/>
				<texcoord u="0.0730633" v="0.20329"/>
			</vertex>
			<vertex>
				<position x="-0.0954387" y="0.888768" z="-0.0344137"/>
				<normal x="0.802276" y="0.280919" z="-0.526724"/>
				<texcoord u="0.0403032" v="0.268158"/>
			</vertex>
			<vertex>
				<position x="-0.00266525" y="0.896121" z="0.00910949"/>
				<normal x="-0.00893167" y="0.173072" z="-0.984869"/>
				<texcoord u="0.0730633" v="0.20329"/>
			</vertex>
			<vertex>
				<position x="-0.00266546" y="0.611711" z="-0.0408701"/>
				<normal x="-0.00612917" y="0.991373" z="-0.130925"/>
				<texcoord u="0.109712" v="0.268158"/>
			</vertex>
			<vertex>
				<position x="-0.00266546" y="0.611711" z="-0.0408701"/>
				<normal x="-0.00612917" y="0.991373" z="-0.130925"/>
				<texcoord u="0.109712" v="0.268158"/>
			</vertex>
			<vertex>
				<position x="0.0877349" y="0.88857" z="-0.0355812"/>
				<normal x="-0.801495" y="0.27188" z="-0.532623"/>
				<texcoord u="0.142406" v="0.20329"/>
			</vertex>
			<vertex>
				<position x="0.0860969" y="0.876037" z="-0.109769"/>
				<normal x="-0.833241" y="0.383601" z="0.398196"/>
				<texcoord u="0.179121" v="0.268158"/>
			</vertex>
			<vertex>
				<position x="-0.00373255" y="-0.0284471" z="-0.09974"/>
				<normal x="0.00707185" y="-0.740842" z="-0.671643"/>
				<texcoord u="0.819347" v="0.987454"/>
			</vertex>
			<vertex>
				<position x="-0.0844387" y="-0.0151036" z="-0.0420298"/>
				<normal x="-0.793669" y="-0.231264" z="-0.562679"/>
				<texcoord u="0.926207" v="0.987454"/>
			</vertex>
			<vertex>
				<position x="-0.09196" y="0.142794" z="-0.067155"/>
				<normal x="-0.896777" y="-0.114211" z="-0.427489"/>
				<texcoord u="0.926207" v="0.820587"/>
			</vertex>
			<vertex>
				<position x="-0.09196" y="0.142794" z="-0.067155"/>
				<normal x="-0.896777" y="-0.114211" z="-0.427489"/>
				<texcoord u="0.926207" v="0.820587"/>
			</vertex>
			<vertex>
				<position x="-0.00373254" y="0.132366" z="-0.130223"/>
				<normal x="0.0178429" y="-0.207681" z="-0.978034"/>
				<texcoord u="0.819347" v="0.820587"/>
			</vertex>
			<vertex>
				<position x="-0.00373255" y="-0.0284471" z="-0.09974"/>
				<normal x="0.00707185" y="-0.740842" z="-0.671643"/>
				<texcoord u="0.819347" v="0.987454"/>
			</vertex>
			<vertex>
				<position x="0.0537258" y="-0.227231" z="-0.0199611"/>
				<normal x="0.682228" y="-0.0972174" z="-0.724648"/>
				<texcoord u="0.715495" v="0.774727"/>
			</vertex>
			<vertex>
				<position x="-0.00373259" y="-0.227203" z="-0.0210335"/>
				<normal x="0.0211148" y="0.0488842" z="-0.998581"/>
				<texcoord u="0.638669" v="0.774727"/>
			</vertex>
			<vertex>
				<position x="-0.00373257" y="-0.0161498" z="-0.0414431"/>
				<normal x="-0.00475936" y="-0.806174" z="-0.591659"/>
				<texcoord u="0.638669" v="0.977362"/>
			</vertex>
			<vertex>
				<position x="-0.00373257" y="-0.0161498" z="-0.0414431"/>
				<normal x="-0.00475936" y="-0.806174" z="-0.591659"/>
				<texcoord u="0.638669" v="0.977362"/>
			</vertex>
			<vertex>
				<position x="0.073739" y="-0.017196" z="-0.0408564"/>
				<normal x="0.806373" y="-0.225634" z="-0.546673"/>
				<texcoord u="0.715495" v="0.977362"/>
			</vertex>
			<vertex>
				<position x="0.0537258" y="-0.227231" z="-0.0199611"/>
				<normal x="0.682228" y="-0.0972174" z="-0.724648"/>
				<texcoord u="0.715495" v="0.774727"/>
			</vertex>
			<vertex>
				<position x="0.0330096" y="-0.355457" z="0.0874647"/>
				<normal x="0.489555" y="-0.234626" z="0.839813"/>
				<texcoord u="0.016124" v="0.46978"/>
			</vertex>
			<vertex>
				<position x="0.043049" y="-0.290426" z="0.0869949"/>
				<normal x="0.691039" y="-0.278405" z="0.66705"/>
				<texcoord u="0.016124" v="0.377282"/>
			</vertex>
			<vertex>
				<position x="-0.0487441" y="-0.289542" z="0.0870624"/>
				<normal x="-0.679615" y="-0.300769" z="0.669075"/>
				<texcoord u="0.016124" v="0.377282"/>
			</vertex>
			<vertex>
				<position x="-0.0487441" y="-0.289542" z="0.0870624"/>
				<normal x="-0.679615" y="-0.300769" z="0.669075"/>
				<texcoord u="0.016124" v="0.377282"/>
			</vertex>
			<vertex>
				<position x="-0.0442045" y="-0.354963" z="0.0862279"/>
				<normal x="-0.554023" y="-0.21911" z="0.80315"/>
				<texcoord u="0.016124" v="0.46978"/>
			</vertex>
			<vertex>
				<position x="0.0330096" y="-0.355457" z="0.0874647"/>
				<normal x="0.489555" y="-0.234626" z="0.839813"/>
				<texcoord u="0.016124" v="0.46978"/>
			</vertex>
			<vertex>
				<position x="-0.0442045" y="-0.354963" z="0.0862279"/>
				<normal x="-0.554023" y="-0.21911" z="0.80315"/>
				<texcoord u="0.016124" v="0.46978"/>
			</vertex>
			<vertex>
				<position x="-0.0473575" y="-0.480912" z="0.0195805"/>
				<normal x="-0.656021" y="-0.0683147" z="0.751644"/>
				<texcoord u="0.016124" v="0.609347"/>
			</vertex>
			<vertex>
				<position x="0.0403442" y="-0.480085" z="0.0200231"/>
				<normal x="0.638015" y="-0.0824735" z="0.765594"/>
				<texcoord u="0.016124" v="0.609347"/>
			</vertex>
			<vertex>
				<position x="0.0403442" y="-0.480085" z="0.0200231"/>
				<normal x="0.638015" y="-0.0824735" z="0.765594"/>
				<texcoord u="0.016124" v="0.609347"/>
			</vertex>
			<vertex>
				<position x="0.0330096" y="-0.355457" z="0.0874647"/>
				<normal x="0.489555" y="-0.234626" z="0.839813"/>
				<texcoord u="0.016124" v="0.46978"/>
			</vertex>
			<vertex>
				<position x="-0.0442045" y="-0.354963" z="0.0862279"/>
				<normal x="-0.554023" y="-0.21911" z="0.80315"/>
				<texcoord u="0.016124" v="0.46978"/>
			</vertex>
			<vertex>
				<position x="-0.0275549" y="-0.310187" z="-0.0387228"/>
				<normal x="-0.448593" y="0.312388" z="-0.837364"/>
				<texcoord u="0.142446" v="0.416183"/>
			</vertex>
			<vertex>
				<position x="-0.0679783" y="-0.227175" z="-0.0221059"/>
				<normal x="-0.700581" y="-0.11783" z="-0.703777"/>
				<texcoord u="0.0950335" v="0.322154"/>
			</vertex>
			<vertex>
				<position x="-0.00373259" y="-0.227203" z="-0.0210335"/>
				<normal x="0.0211148" y="0.0488842" z="-0.998581"/>
				<texcoord u="0.189523" v="0.322154"/>
			</vertex>
			<vertex>
				<position x="-0.00373259" y="-0.227203" z="-0.0210335"/>
				<normal x="0.0211148" y="0.0488842" z="-0.998581"/>
				<texcoord u="0.189523" v="0.322154"/>
			</vertex>
			<vertex>
				<position x="-0.00373259" y="-0.311601" z="-0.0376956"/>
				<normal x="0.0806883" y="0.45424" z="-0.887218"/>
				<texcoord u="0.189523" v="0.409772"/>
			</vertex>
			<vertex>
				<position x="-0.0275549" y="-0.310187" z="-0.0387228"/>
				<normal x="-0.448593" y="0.312388" z="-0.837364"/>
				<texcoord u="0.142446" v="0.416183"/>
			</vertex>
			<vertex>
				<position x="-0.0903458" y="-0.00869397" z="0.022208"/>
				<normal x="-0.000409251" y="0.217796" z="0.975994"/>
				<texcoord u="0.72199" v="0.641852"/>
			</vertex>
			<vertex>
				<position x="0.0776454" y="-0.00828766" z="0.0219938"/>
				<normal x="0.000721086" y="0.216706" z="0.976237"/>
				<texcoord u="0.551319" v="0.641852"/>
			</vertex>
			<vertex>
				<position x="0.0761077" y="0.155782" z="-0.0144256"/>
				<normal x="-0.000635797" y="0.156395" z="0.987694"/>
				<texcoord u="0.551319" v="0.768697"/>
			</vertex>
			<vertex>
				<position x="0.0761077" y="0.155782" z="-0.0144256"/>
				<normal x="-0.000635797" y="0.156395" z="0.987694"/>
				<texcoord u="0.551319" v="0.768697"/>
			</vertex>
			<vertex>
				<position x="-0.0896139" y="0.155773" z="-0.0146886"/>
				<normal x="-0.00157549" y="0.15647" z="0.987682"/>
				<texcoord u="0.72199" v="0.768461"/>
			</vertex>
			<vertex>
				<position x="-0.0903458" y="-0.00869397" z="0.022208"/>
				<normal x="-0.000409251" y="0.217796" z="0.975994"/>
				<texcoord u="0.72199" v="0.641852"/>
			</vertex>
			<vertex>
				<position x="-0.0903458" y="-0.00869397" z="0.022208"/>
				<normal x="-0.000762469" y="0.99353" z="-0.113565"/>
				<texcoord u="0.72199" v="0.641852"/>
			</vertex>
			<vertex>
				<position x="-0.0774943" y="0.00525699" z="0.142349"/>
				<normal x="0.000617899" y="0.993318" z="-0.115412"/>
				<texcoord u="0.721977" v="0.496556"/>
			</vertex>
			<vertex>
				<position x="0.0733755" y="0.00523522" z="0.142969"/>
				<normal x="-0.00129218" y="0.993611" z="-0.112856"/>
				<texcoord u="0.551012" v="0.496514"/>
			</vertex>
			<vertex>
				<position x="0.0733755" y="0.00523522" z="0.142969"/>
				<normal x="-0.00129218" y="0.993611" z="-0.112856"/>
				<texcoord u="0.551012" v="0.496514"/>
			</vertex>
			<vertex>
				<position x="0.0776454" y="-0.00828766" z="0.0219938"/>
				<normal x="-0.00254547" y="0.993797" z="-0.111178"/>
				<texcoord u="0.551319" v="0.641852"/>
			</vertex>
			<vertex>
				<position x="-0.0903458" y="-0.00869397" z="0.022208"/>
				<normal x="-0.000762469" y="0.99353" z="-0.113565"/>
				<texcoord u="0.72199" v="0.641852"/>
			</vertex>
			<vertex>
				<position x="0.043049" y="-0.290426" z="0.0869949"/>
				<normal x="0.691039" y="-0.278405" z="0.66705"/>
				<texcoord u="0.551319" v="0.257215"/>
			</vertex>
			<vertex>
				<position x="0.0627304" y="-0.176763" z="0.16468"/>
				<normal x="0.61977" y="-0.237191" z="0.748081"/>
				<texcoord u="0.551418" v="0.386217"/>
			</vertex>
			<vertex>
				<position x="-0.0699016" y="-0.177235" z="0.166817"/>
				<normal x="-0.597108" y="-0.240795" z="0.765167"/>
				<texcoord u="0.721424" v="0.386148"/>
			</vertex>
			<vertex>
				<position x="-0.0699016" y="-0.177235" z="0.166817"/>
				<normal x="-0.597108" y="-0.240795" z="0.765167"/>
				<texcoord u="0.721424" v="0.386148"/>
			</vertex>
			<vertex>
				<position x="-0.0487441" y="-0.289542" z="0.0870624"/>
				<normal x="-0.679615" y="-0.300769" z="0.669075"/>
				<texcoord u="0.72199" v="0.257215"/>
			</vertex>
			<vertex>
				<position x="0.043049" y="-0.290426" z="0.0869949"/>
				<normal x="0.691039" y="-0.278405" z="0.66705"/>
				<texcoord u="0.551319" v="0.257215"/>
			</vertex>
			<vertex>
				<position x="-0.00373254" y="0.330642" z="-0.176954"/>
				<normal x="-0.00194396" y="0.599086" z="-0.800682"/>
				<texcoord u="0.441007" v="0.749174"/>
			</vertex>
			<vertex>
				<position x="-0.113531" y="0.416837" z="-0.112194"/>
				<normal x="0.00489538" y="0.951328" z="-0.308141"/>
				<texcoord u="0.53331" v="0.666269"/>
			</vertex>
			<vertex>
				<position x="0.100199" y="0.416169" z="-0.113213"/>
				<normal x="0.00148164" y="0.949961" z="-0.312365"/>
				<texcoord u="0.344139" v="0.666269"/>
			</vertex>
			<vertex>
				<position x="-0.113531" y="0.416837" z="-0.112194"/>
				<normal x="0.00489538" y="0.951328" z="-0.308141"/>
				<texcoord u="0.53331" v="0.666269"/>
			</vertex>
			<vertex>
				<position x="-0.110068" y="0.418355" z="-0.0401058"/>
				<normal x="0.00898175" y="0.999729" z="-0.0214715"/>
				<texcoord u="0.522901" v="0.607163"/>
			</vertex>
			<vertex>
				<position x="0.0950713" y="0.416514" z="-0.0399664"/>
				<normal x="0.00429809" y="0.999959" z="-0.00794345"/>
				<texcoord u="0.360242" v="0.607163"/>
			</vertex>
			<vertex>
				<position x="0.0950713" y="0.416514" z="-0.0399664"/>
				<normal x="0.00429809" y="0.999959" z="-0.00794345"/>
				<texcoord u="0.360242" v="0.607163"/>
			</vertex>
			<vertex>
				<position x="0.100199" y="0.416169" z="-0.113213"/>
				<normal x="0.00148164" y="0.949961" z="-0.312365"/>
				<texcoord u="0.344139" v="0.666269"/>
			</vertex>
			<vertex>
				<position x="-0.113531" y="0.416837" z="-0.112194"/>
				<normal x="0.00489538" y="0.951328" z="-0.308141"/>
				<texcoord u="0.53331" v="0.666269"/>
			</vertex>
			<vertex>
				<position x="0.043049" y="-0.290426" z="0.0869949"/>
				<normal x="0.691039" y="-0.278405" z="0.66705"/>
				<texcoord u="0.016124" v="0.377282"/>
			</vertex>
			<vertex>
				<position x="0.0633201" y="-0.329628" z="0.0182768"/>
				<normal x="0.997753" y="0.049405" z="-0.0452498"/>
				<texcoord u="0.0576082" v="0.441465"/>
			</vertex>
			<vertex>
				<position x="0.0537258" y="-0.227231" z="-0.0199611"/>
				<normal x="0.682228" y="-0.0972174" z="-0.724648"/>
				<texcoord u="0.0950335" v="0.322154"/>
			</vertex>
			<vertex>
				<position x="-0.0275549" y="-0.310187" z="-0.0387228"/>
				<normal x="-0.448593" y="0.312388" z="-0.837364"/>
				<texcoord u="0.142446" v="0.416183"/>
			</vertex>
			<vertex>
				<position x="-0.0642376" y="-0.332824" z="0.0222099"/>
				<normal x="-0.99992" y="0.0114969" z="0.00525182"/>
				<texcoord u="0.0576082" v="0.441465"/>
			</vertex>
			<vertex>
				<position x="-0.0679783" y="-0.227175" z="-0.0221059"/>
				<normal x="-0.700581" y="-0.11783" z="-0.703777"/>
				<texcoord u="0.0950335" v="0.322154"/>
			</vertex>
			<vertex>
				<position x="0.0712535" y="-0.208594" z="0.0456767"/>
				<normal x="0.979188" y="-0.198044" z="-0.044385"/>
				<texcoord u="0.820393" v="0.495198"/>
			</vertex>
			<vertex>
				<position x="0.043049" y="-0.290426" z="0.0869949"/>
				<normal x="0.691039" y="-0.278405" z="0.66705"/>
				<texcoord u="0.830433" v="0.61201"/>
			</vertex>
			<vertex>
				<position x="0.0537258" y="-0.227231" z="-0.0199611"/>
				<normal x="0.682228" y="-0.0972174" z="-0.724648"/>
				<texcoord u="0.732508" v="0.504887"/>
			</vertex>
			<vertex>
				<position x="-0.0699016" y="-0.177235" z="0.166817"/>
				<normal x="-0.597108" y="-0.240795" z="0.765167"/>
				<texcoord u="0.984355" v="0.489578"/>
			</vertex>
			<vertex>
				<position x="-0.0759226" y="-0.030984" z="0.156507"/>
				<normal x="-0.640662" y="0.139876" z="0.754975"/>
				<texcoord u="0.984355" v="0.292055"/>
			</vertex>
			<vertex>
				<position x="-0.0903458" y="-0.00869397" z="0.022208"/>
				<normal x="-0.99904" y="-0.041812" z="-0.0130468"/>
				<texcoord u="0.819446" v="0.247971"/>
			</vertex>
			<vertex>
				<position x="-0.0903458" y="-0.00869397" z="0.022208"/>
				<normal x="-0.99904" y="-0.041812" z="-0.0130468"/>
				<texcoord u="0.819446" v="0.247971"/>
			</vertex>
			<vertex>
				<position x="-0.081786" y="-0.208362" z="0.0479448"/>
				<normal x="-0.977694" y="-0.210032" z="0.00101598"/>
				<texcoord u="0.820393" v="0.495198"/>
			</vertex>
			<vertex>
				<position x="-0.0699016" y="-0.177235" z="0.166817"/>
				<normal x="-0.597108" y="-0.240795" z="0.765167"/>
				<texcoord u="0.984355" v="0.489578"/>
			</vertex>
			<vertex>
				<position x="0.0761077" y="0.155782" z="-0.0144256"/>
				<normal x="0.998446" y="-0.0284067" z="0.0479465"/>
				<texcoord u="0.987881" v="0.820587"/>
			</vertex>
			<vertex>
				<position x="0.0782096" y="0.142911" z="-0.0670936"/>
				<normal x="0.903416" y="-0.108923" z="-0.414699"/>
				<texcoord u="0.926207" v="0.820587"/>
			</vertex>
			<vertex>
				<position x="0.100199" y="0.416169" z="-0.113213"/>
				<normal x="0.941963" y="-0.126714" z="-0.310886"/>
				<texcoord u="0.926207" v="0.551077"/>
			</vertex>
			<vertex>
				<position x="0.100199" y="0.416169" z="-0.113213"/>
				<normal x="0.941963" y="-0.126714" z="-0.310886"/>
				<texcoord u="0.926207" v="0.551077"/>
			</vertex>
			<vertex>
				<position x="0.0950713" y="0.416514" z="-0.0399664"/>
				<normal x="0.995392" y="-0.0655409" z="0.0699908"/>
				<texcoord u="0.987881" v="0.564336"/>
			</vertex>
			<vertex>
				<position x="0.0761077" y="0.155782" z="-0.0144256"/>
				<normal x="0.998446" y="-0.0284067" z="0.0479465"/>
				<texcoord u="0.987881" v="0.820587"/>
			</vertex>
			<vertex>
				<position x="-0.09196" y="0.142794" z="-0.067155"/>
				<normal x="-0.896777" y="-0.114211" z="-0.427489"/>
				<texcoord u="0.926207" v="0.820587"/>
			</vertex>
			<vertex>
				<position x="-0.0844387" y="-0.0151036" z="-0.0420298"/>
				<normal x="-0.793669" y="-0.231264" z="-0.562679"/>
				<texcoord u="0.926207" v="0.987454"/>
			</vertex>
			<vertex>
				<position x="-0.0903458" y="-0.00869397" z="0.022208"/>
				<normal x="-0.99904" y="-0.041812" z="-0.0130468"/>
				<texcoord u="0.987881" v="0.987454"/>
			</vertex>
			<vertex>
				<position x="-0.0903458" y="-0.00869397" z="0.022208"/>
				<normal x="-0.99904" y="-0.041812" z="-0.0130468"/>
				<texcoord u="0.987881" v="0.987454"/>
			</vertex>
			<vertex>
				<position x="-0.0896139" y="0.155773" z="-0.0146886"/>
				<normal x="-0.998259" y="-0.0297399" z="0.0509443"/>
				<texcoord u="0.987881" v="0.820587"/>
			</vertex>
			<vertex>
				<position x="-0.09196" y="0.142794" z="-0.067155"/>
				<normal x="-0.896777" y="-0.114211" z="-0.427489"/>
				<texcoord u="0.926207" v="0.820587"/>
			</vertex>
			<vertex>
				<position x="0.073739" y="-0.017196" z="-0.0408564"/>
				<normal x="0.806373" y="-0.225634" z="-0.546673"/>
				<texcoord u="0.926207" v="0.987454"/>
			</vertex>
			<vertex>
				<position x="-0.00373255" y="-0.0284471" z="-0.09974"/>
				<normal x="0.00707185" y="-0.740842" z="-0.671643"/>
				<texcoord u="0.819347" v="0.987454"/>
			</vertex>
			<vertex>
				<position x="-0.00373254" y="0.132366" z="-0.130223"/>
				<normal x="0.0178429" y="-0.207681" z="-0.978034"/>
				<texcoord u="0.819347" v="0.820587"/>
			</vertex>
			<vertex>
				<position x="-0.00373254" y="0.132366" z="-0.130223"/>
				<normal x="0.0178429" y="-0.207681" z="-0.978034"/>
				<texcoord u="0.819347" v="0.820587"/>
			</vertex>
			<vertex>
				<position x="0.0782096" y="0.142911" z="-0.0670936"/>
				<normal x="0.903416" y="-0.108923" z="-0.414699"/>
				<texcoord u="0.926207" v="0.820587"/>
			</vertex>
			<vertex>
				<position x="0.073739" y="-0.017196" z="-0.0408564"/>
				<normal x="0.806373" y="-0.225634" z="-0.546673"/>
				<texcoord u="0.926207" v="0.987454"/>
			</vertex>
			<vertex>
				<position x="0.0712535" y="-0.208594" z="0.0456767"/>
				<normal x="0.979188" y="-0.198044" z="-0.044385"/>
				<texcoord u="0.820393" v="0.495198"/>
			</vertex>
			<vertex>
				<position x="0.0537258" y="-0.227231" z="-0.0199611"/>
				<normal x="0.682228" y="-0.0972174" z="-0.724648"/>
				<texcoord u="0.732508" v="0.504887"/>
			</vertex>
			<vertex>
				<position x="0.073739" y="-0.017196" z="-0.0408564"/>
				<normal x="0.806373" y="-0.225634" z="-0.546673"/>
				<texcoord u="0.732508" v="0.247971"/>
			</vertex>
			<vertex>
				<position x="0.073739" y="-0.017196" z="-0.0408564"/>
				<normal x="0.806373" y="-0.225634" z="-0.546673"/>
				<texcoord u="0.732508" v="0.247971"/>
			</vertex>
			<vertex>
				<position x="0.0776454" y="-0.00828766" z="0.0219938"/>
				<normal x="0.999288" y="-0.0354372" z="-0.0129603"/>
				<texcoord u="0.819446" v="0.247971"/>
			</vertex>
			<vertex>
				<position x="0.0712535" y="-0.208594" z="0.0456767"/>
				<normal x="0.979188" y="-0.198044" z="-0.044385"/>
				<texcoord u="0.820393" v="0.495198"/>
			</vertex>
			<vertex>
				<position x="-0.0487441" y="-0.289542" z="0.0870624"/>
				<normal x="-0.679615" y="-0.300769" z="0.669075"/>
				<texcoord u="0.830433" v="0.61201"/>
			</vertex>
			<vertex>
				<position x="-0.0699016" y="-0.177235" z="0.166817"/>
				<normal x="-0.597108" y="-0.240795" z="0.765167"/>
				<texcoord u="0.984355" v="0.489578"/>
			</vertex>
			<vertex>
				<position x="-0.081786" y="-0.208362" z="0.0479448"/>
				<normal x="-0.977694" y="-0.210032" z="0.00101598"/>
				<texcoord u="0.820393" v="0.495198"/>
			</vertex>
			<vertex>
				<position x="0.0776454" y="-0.00828766" z="0.0219938"/>
				<normal x="0.999288" y="-0.0354372" z="-0.0129603"/>
				<texcoord u="0.819446" v="0.247971"/>
			</vertex>
			<vertex>
				<position x="0.071519" y="-0.0249843" z="0.155756"/>
				<normal x="0.659358" y="0.1406" z="0.738566"/>
				<texcoord u="0.984355" v="0.292055"/>
			</vertex>
			<vertex>
				<position x="0.0627304" y="-0.176763" z="0.16468"/>
				<normal x="0.61977" y="-0.237191" z="0.748081"/>
				<texcoord u="0.984355" v="0.489578"/>
			</vertex>
			<vertex>
				<position x="0.0627304" y="-0.176763" z="0.16468"/>
				<normal x="0.61977" y="-0.237191" z="0.748081"/>
				<texcoord u="0.984355" v="0.489578"/>
			</vertex>
			<vertex>
				<position x="0.0712535" y="-0.208594" z="0.0456767"/>
				<normal x="0.979188" y="-0.198044" z="-0.044385"/>
				<texcoord u="0.820393" v="0.495198"/>
			</vertex>
			<vertex>
				<position x="0.0776454" y="-0.00828766" z="0.0219938"/>
				<normal x="0.999288" y="-0.0354372" z="-0.0129603"/>
				<texcoord u="0.819446" v="0.247971"/>
			</vertex>
			<vertex>
				<position x="0.0712535" y="-0.208594" z="0.0456767"/>
				<normal x="0.979188" y="-0.198044" z="-0.044385"/>
				<texcoord u="0.820393" v="0.495198"/>
			</vertex>
			<vertex>
				<position x="0.0627304" y="-0.176763" z="0.16468"/>
				<normal x="0.61977" y="-0.237191" z="0.748081"/>
				<texcoord u="0.984355" v="0.489578"/>
			</vertex>
			<vertex>
				<position x="0.043049" y="-0.290426" z="0.0869949"/>
				<normal x="0.691039" y="-0.278405" z="0.66705"/>
				<texcoord u="0.830433" v="0.61201"/>
			</vertex>
			<vertex>
				<position x="-0.081786" y="-0.208362" z="0.0479448"/>
				<normal x="-0.977694" y="-0.210032" z="0.00101598"/>
				<texcoord u="0.820393" v="0.495198"/>
			</vertex>
			<vertex>
				<position x="-0.0903458" y="-0.00869397" z="0.022208"/>
				<normal x="-0.99904" y="-0.041812" z="-0.0130468"/>
				<texcoord u="0.819446" v="0.247971"/>
			</vertex>
			<vertex>
				<position x="-0.0844387" y="-0.0151036" z="-0.0420298"/>
				<normal x="-0.793669" y="-0.231264" z="-0.562679"/>
				<texcoord u="0.732508" v="0.247971"/>
			</vertex>
			<vertex>
				<position x="-0.0844387" y="-0.0151036" z="-0.0420298"/>
				<normal x="-0.793669" y="-0.231264" z="-0.562679"/>
				<texcoord u="0.732508" v="0.247971"/>
			</vertex>
			<vertex>
				<position x="-0.0679783" y="-0.227175" z="-0.0221059"/>
				<normal x="-0.700581" y="-0.11783" z="-0.703777"/>
				<texcoord u="0.732508" v="0.504887"/>
			</vertex>
			<vertex>
				<position x="-0.081786" y="-0.208362" z="0.0479448"/>
				<normal x="-0.977694" y="-0.210032" z="0.00101598"/>
				<texcoord u="0.820393" v="0.495198"/>
			</vertex>
			<vertex>
				<position x="-0.081786" y="-0.208362" z="0.0479448"/>
				<normal x="-0.977694" y="-0.210032" z="0.00101598"/>
				<texcoord u="0.820393" v="0.495198"/>
			</vertex>
			<vertex>
				<position x="-0.0679783" y="-0.227175" z="-0.0221059"/>
				<normal x="-0.700581" y="-0.11783" z="-0.703777"/>
				<texcoord u="0.732508" v="0.504887"/>
			</vertex>
			<vertex>
				<position x="-0.0487441" y="-0.289542" z="0.0870624"/>
				<normal x="-0.679615" y="-0.300769" z="0.669075"/>
				<texcoord u="0.830433" v="0.61201"/>
			</vertex>
			<vertex>
				<position x="-0.00373254" y="0.330642" z="-0.176954"/>
				<normal x="0.0156938" y="-0.224725" z="-0.974296"/>
				<texcoord u="0.819347" v="0.627864"/>
			</vertex>
			<vertex>
				<position x="-0.00373254" y="0.132366" z="-0.130223"/>
				<normal x="0.0178429" y="-0.207681" z="-0.978034"/>
				<texcoord u="0.819347" v="0.820587"/>
			</vertex>
			<vertex>
				<position x="-0.09196" y="0.142794" z="-0.067155"/>
				<normal x="-0.896777" y="-0.114211" z="-0.427489"/>
				<texcoord u="0.926207" v="0.820587"/>
			</vertex>
			<vertex>
				<position x="-0.09196" y="0.142794" z="-0.067155"/>
				<normal x="-0.896777" y="-0.114211" z="-0.427489"/>
				<texcoord u="0.926207" v="0.820587"/>
			</vertex>
			<vertex>
				<position x="-0.113531" y="0.416837" z="-0.112194"/>
				<normal x="-0.935453" y="-0.129146" z="-0.329014"/>
				<texcoord u="0.926207" v="0.551077"/>
			</vertex>
			<vertex>
				<position x="-0.00373254" y="0.330642" z="-0.176954"/>
				<normal x="0.0156938" y="-0.224725" z="-0.974296"/>
				<texcoord u="0.819347" v="0.627864"/>
			</vertex>
			<vertex>
				<position x="-0.110068" y="0.418355" z="-0.0401058"/>
				<normal x="-0.000446779" y="0.0970241" z="0.995282"/>
				<texcoord u="0.72199" v="0.991475"/>
			</vertex>
			<vertex>
				<position x="-0.0896139" y="0.155773" z="-0.0146886"/>
				<normal x="-0.00157549" y="0.15647" z="0.987682"/>
				<texcoord u="0.72199" v="0.768461"/>
			</vertex>
			<vertex>
				<position x="0.0761077" y="0.155782" z="-0.0144256"/>
				<normal x="-0.000635797" y="0.156395" z="0.987694"/>
				<texcoord u="0.551319" v="0.768697"/>
			</vertex>
			<vertex>
				<position x="0.0761077" y="0.155782" z="-0.0144256"/>
				<normal x="-0.000635797" y="0.156395" z="0.987694"/>
				<texcoord u="0.551319" v="0.768697"/>
			</vertex>
			<vertex>
				<position x="0.0950713" y="0.416514" z="-0.0399664"/>
				<normal x="0.000198303" y="0.0974772" z="0.995238"/>
				<texcoord u="0.551319" v="0.991475"/>
			</vertex>
			<vertex>
				<position x="-0.110068" y="0.418355" z="-0.0401058"/>
				<normal x="-0.000446779" y="0.0970241" z="0.995282"/>
				<texcoord u="0.72199" v="0.991475"/>
			</vertex>
			<vertex>
				<position x="0.0782096" y="0.142911" z="-0.0670936"/>
				<normal x="0.903416" y="-0.108923" z="-0.414699"/>
				<texcoord u="0.926207" v="0.820587"/>
			</vertex>
			<vertex>
				<position x="0.0761077" y="0.155782" z="-0.0144256"/>
				<normal x="0.998446" y="-0.0284067" z="0.0479465"/>
				<texcoord u="0.987881" v="0.820587"/>
			</vertex>
			<vertex>
				<position x="0.0776454" y="-0.00828766" z="0.0219938"/>
				<normal x="0.999288" y="-0.0354372" z="-0.0129603"/>
				<texcoord u="0.987881" v="0.987454"/>
			</vertex>
			<vertex>
				<position x="0.0776454" y="-0.00828766" z="0.0219938"/>
				<normal x="0.999288" y="-0.0354372" z="-0.0129603"/>
				<texcoord u="0.987881" v="0.987454"/>
			</vertex>
			<vertex>
				<position x="0.073739" y="-0.017196" z="-0.0408564"/>
				<normal x="0.806373" y="-0.225634" z="-0.546673"/>
				<texcoord u="0.926207" v="0.987454"/>
			</vertex>
			<vertex>
				<position x="0.0782096" y="0.142911" z="-0.0670936"/>
				<normal x="0.903416" y="-0.108923" z="-0.414699"/>
				<texcoord u="0.926207" v="0.820587"/>
			</vertex>
			<vertex>
				<position x="-0.113531" y="0.416837" z="-0.112194"/>
				<normal x="-0.935453" y="-0.129146" z="-0.329014"/>
				<texcoord u="0.926207" v="0.551077"/>
			</vertex>
			<vertex>
				<position x="-0.09196" y="0.142794" z="-0.067155"/>
				<normal x="-0.896777" y="-0.114211" z="-0.427489"/>
				<texcoord u="0.926207" v="0.820587"/>
			</vertex>
			<vertex>
				<position x="-0.0896139" y="0.155773" z="-0.0146886"/>
				<normal x="-0.998259" y="-0.0297399" z="0.0509443"/>
				<texcoord u="0.987881" v="0.820587"/>
			</vertex>
			<vertex>
				<position x="-0.0896139" y="0.155773" z="-0.0146886"/>
				<normal x="-0.998259" y="-0.0297399" z="0.0509443"/>
				<texcoord u="0.987881" v="0.820587"/>
			</vertex>
			<vertex>
				<position x="-0.110068" y="0.418355" z="-0.0401058"/>
				<normal x="-0.996122" y="-0.0728152" z="0.0493828"/>
				<texcoord u="0.987881" v="0.564336"/>
			</vertex>
			<vertex>
				<position x="-0.113531" y="0.416837" z="-0.112194"/>
				<normal x="-0.935453" y="-0.129146" z="-0.329014"/>
				<texcoord u="0.926207" v="0.551077"/>
			</vertex>
			<vertex>
				<position x="0.0782096" y="0.142911" z="-0.0670936"/>
				<normal x="0.903416" y="-0.108923" z="-0.414699"/>
				<texcoord u="0.926207" v="0.820587"/>
			</vertex>
			<vertex>
				<position x="-0.00373254" y="0.132366" z="-0.130223"/>
				<normal x="0.0178429" y="-0.207681" z="-0.978034"/>
				<texcoord u="0.819347" v="0.820587"/>
			</vertex>
			<vertex>
				<position x="-0.00373254" y="0.330642" z="-0.176954"/>
				<normal x="0.0156938" y="-0.224725" z="-0.974296"/>
				<texcoord u="0.819347" v="0.627864"/>
			</vertex>
			<vertex>
				<position x="-0.00373254" y="0.330642" z="-0.176954"/>
				<normal x="0.0156938" y="-0.224725" z="-0.974296"/>
				<texcoord u="0.819347" v="0.627864"/>
			</vertex>
			<vertex>
				<position x="0.100199" y="0.416169" z="-0.113213"/>
				<normal x="0.941963" y="-0.126714" z="-0.310886"/>
				<texcoord u="0.926207" v="0.551077"/>
			</vertex>
			<vertex>
				<position x="0.0782096" y="0.142911" z="-0.0670936"/>
				<normal x="0.903416" y="-0.108923" z="-0.414699"/>
				<texcoord u="0.926207" v="0.820587"/>
			</vertex>
			<vertex>
				<position x="-0.00373255" y="-0.0284471" z="-0.09974"/>
				<normal x="0.00707185" y="-0.740842" z="-0.671643"/>
				<texcoord u="0.51655" v="0.851527"/>
			</vertex>
			<vertex>
				<position x="-0.00373257" y="-0.0161498" z="-0.0414431"/>
				<normal x="-0.00475936" y="-0.806174" z="-0.591659"/>
				<texcoord u="0.46304" v="0.866961"/>
			</vertex>
			<vertex>
				<position x="-0.0844387" y="-0.0151036" z="-0.0420298"/>
				<normal x="-0.793669" y="-0.231264" z="-0.562679"/>
				<texcoord u="0.51502" v="0.978049"/>
			</vertex>
			<vertex>
				<position x="-0.0037325" y="-0.421575" z="-0.141109"/>
				<normal x="0.00714522" y="0.472086" z="-0.881523"/>
				<texcoord u="0.267738" v="0.546036"/>
			</vertex>
			<vertex>
				<position x="-0.0676773" y="-0.791684" z="-0.222563"/>
				<normal x="-0.482345" y="-0.439791" z="-0.75758"/>
				<texcoord u="0.317736" v="0.944003"/>
			</vertex>
			<vertex>
				<position x="-0.0787285" y="-0.446506" z="-0.0716158"/>
				<normal x="-0.949783" y="0.209363" z="-0.232552"/>
				<texcoord u="0.144428" v="0.587824"/>
			</vertex>
			<vertex>
				<position x="-0.0642376" y="-0.332824" z="0.0222099"/>
				<normal x="-0.99992" y="0.0114969" z="0.00525182"/>
				<texcoord u="0.0576082" v="0.441465"/>
			</vertex>
			<vertex>
				<position x="-0.0787285" y="-0.446506" z="-0.0716158"/>
				<normal x="-0.949783" y="0.209363" z="-0.232552"/>
				<texcoord u="0.144428" v="0.587824"/>
			</vertex>
			<vertex>
				<position x="-0.0473575" y="-0.480912" z="0.0195805"/>
				<normal x="-0.656021" y="-0.0683147" z="0.751644"/>
				<texcoord u="0.016124" v="0.609347"/>
			</vertex>
			<vertex>
				<position x="-0.0473575" y="-0.480912" z="0.0195805"/>
				<normal x="-0.656021" y="-0.0683147" z="0.751644"/>
				<texcoord u="0.016124" v="0.609347"/>
			</vertex>
			<vertex>
				<position x="-0.0442045" y="-0.354963" z="0.0862279"/>
				<normal x="-0.554023" y="-0.21911" z="0.80315"/>
				<texcoord u="0.016124" v="0.46978"/>
			</vertex>
			<vertex>
				<position x="-0.0642376" y="-0.332824" z="0.0222099"/>
				<normal x="-0.99992" y="0.0114969" z="0.00525182"/>
				<texcoord u="0.0576082" v="0.441465"/>
			</vertex>
			<vertex>
				<position x="0.0568841" y="-0.802273" z="0.059225"/>
				<normal x="0.490296" y="-0.524635" z="0.695965"/>
				<texcoord u="0.016124" v="0.981184"/>
			</vertex>
			<vertex>
				<position x="0.0398403" y="-0.649002" z="0.0577472"/>
				<normal x="0.52935" y="0.121825" z="0.839611"/>
				<texcoord u="0.016124" v="0.816589"/>
			</vertex>
			<vertex>
				<position x="-0.0491411" y="-0.648708" z="0.0584578"/>
				<normal x="-0.536282" y="0.128326" z="0.834227"/>
				<texcoord u="0.016124" v="0.816589"/>
			</vertex>
			<vertex>
				<position x="-0.0491411" y="-0.648708" z="0.0584578"/>
				<normal x="-0.536282" y="0.128326" z="0.834227"/>
				<texcoord u="0.016124" v="0.816589"/>
			</vertex>
			<vertex>
				<position x="-0.0632587" y="-0.801396" z="0.0621366"/>
				<normal x="-0.478709" y="-0.519743" z="0.707605"/>
				<texcoord u="0.016124" v="0.981184"/>
			</vertex>
			<vertex>
				<position x="0.0568841" y="-0.802273" z="0.059225"/>
				<normal x="0.490296" y="-0.524635" z="0.695965"/>
				<texcoord u="0.016124" v="0.981184"/>
			</vertex>
			<vertex>
				<position x="0.109295" y="-0.819927" z="-0.0754877"/>
				<normal x="0.77053" y="-0.637402" z="-0.00123026"/>
				<texcoord u="0.353907" v="0.982426"/>
			</vertex>
			<vertex>
				<position x="0.0568841" y="-0.802273" z="0.059225"/>
				<normal x="0.490296" y="-0.524635" z="0.695965"/>
				<texcoord u="0.388235" v="0.919397"/>
			</vertex>
			<vertex>
				<position x="-0.0632587" y="-0.801396" z="0.0621366"/>
				<normal x="-0.478709" y="-0.519743" z="0.707605"/>
				<texcoord u="0.46098" v="0.919397"/>
			</vertex>
			<vertex>
				<position x="-0.0632587" y="-0.801396" z="0.0621366"/>
				<normal x="-0.478709" y="-0.519743" z="0.707605"/>
				<texcoord u="0.46098" v="0.919397"/>
			</vertex>
			<vertex>
				<position x="-0.115993" y="-0.819207" z="-0.0776441"/>
				<normal x="-0.770807" y="-0.637064" z="-0.00257524"/>
				<texcoord u="0.486437" v="0.982426"/>
			</vertex>
			<vertex>
				<position x="0.109295" y="-0.819927" z="-0.0754877"/>
				<normal x="0.77053" y="-0.637402" z="-0.00123026"/>
				<texcoord u="0.353907" v="0.982426"/>
			</vertex>
			<vertex>
				<position x="0.109295" y="-0.819927" z="-0.0754877"/>
				<normal x="0.77053" y="-0.637402" z="-0.00123026"/>
				<texcoord u="0.156454" v="0.981184"/>
			</vertex>
			<vertex>
				<position x="0.0398403" y="-0.649002" z="0.0577472"/>
				<normal x="0.52935" y="0.121825" z="0.839611"/>
				<texcoord u="0.016124" v="0.816589"/>
			</vertex>
			<vertex>
				<position x="0.0568841" y="-0.802273" z="0.059225"/>
				<normal x="0.490296" y="-0.524635" z="0.695965"/>
				<texcoord u="0.016124" v="0.981184"/>
			</vertex>
			<vertex>
				<position x="0.0570305" y="-0.791962" z="-0.221993"/>
				<normal x="0.474012" y="-0.444544" z="-0.760061"/>
				<texcoord u="0.388235" v="0.919397"/>
			</vertex>
			<vertex>
				<position x="0.109295" y="-0.819927" z="-0.0754877"/>
				<normal x="0.77053" y="-0.637402" z="-0.00123026"/>
				<texcoord u="0.353907" v="0.982426"/>
			</vertex>
			<vertex>
				<position x="-0.115993" y="-0.819207" z="-0.0776441"/>
				<normal x="-0.770807" y="-0.637064" z="-0.00257524"/>
				<texcoord u="0.486437" v="0.982426"/>
			</vertex>
			<vertex>
				<position x="-0.115993" y="-0.819207" z="-0.0776441"/>
				<normal x="-0.770807" y="-0.637064" z="-0.00257524"/>
				<texcoord u="0.486437" v="0.982426"/>
			</vertex>
			<vertex>
				<position x="-0.0676773" y="-0.791684" z="-0.222563"/>
				<normal x="-0.482345" y="-0.439791" z="-0.75758"/>
				<texcoord u="0.46098" v="0.919397"/>
			</vertex>
			<vertex>
				<position x="0.0570305" y="-0.791962" z="-0.221993"/>
				<normal x="0.474012" y="-0.444544" z="-0.760061"/>
				<texcoord u="0.388235" v="0.919397"/>
			</vertex>
			<vertex>
				<position x="0.0403442" y="-0.480085" z="0.0200231"/>
				<normal x="0.638015" y="-0.0824735" z="0.765594"/>
				<texcoord u="0.016124" v="0.609347"/>
			</vertex>
			<vertex>
				<position x="0.074935" y="-0.449712" z="-0.0694957"/>
				<normal x="0.95086" y="0.212898" z="-0.224809"/>
				<texcoord u="0.144428" v="0.587824"/>
			</vertex>
			<vertex>
				<position x="0.0633201" y="-0.329628" z="0.0182768"/>
				<normal x="0.997753" y="0.049405" z="-0.0452498"/>
				<texcoord u="0.0576082" v="0.441465"/>
			</vertex>
			<vertex>
				<position x="0.0633201" y="-0.329628" z="0.0182768"/>
				<normal x="0.997753" y="0.049405" z="-0.0452498"/>
				<texcoord u="0.0576082" v="0.441465"/>
			</vertex>
			<vertex>
				<position x="0.0330096" y="-0.355457" z="0.0874647"/>
				<normal x="0.489555" y="-0.234626" z="0.839813"/>
				<texcoord u="0.016124" v="0.46978"/>
			</vertex>
			<vertex>
				<position x="0.0403442" y="-0.480085" z="0.0200231"/>
				<normal x="0.638015" y="-0.0824735" z="0.765594"/>
				<texcoord u="0.016124" v="0.609347"/>
			</vertex>
			<vertex>
				<position x="-0.0787285" y="-0.446506" z="-0.0716158"/>
				<normal x="-0.949783" y="0.209363" z="-0.232552"/>
				<texcoord u="0.144428" v="0.587824"/>
			</vertex>
			<vertex>
				<position x="-0.0642376" y="-0.332824" z="0.0222099"/>
				<normal x="-0.99992" y="0.0114969" z="0.00525182"/>
				<texcoord u="0.0576082" v="0.441465"/>
			</vertex>
			<vertex>
				<position x="-0.0275549" y="-0.310187" z="-0.0387228"/>
				<normal x="-0.448593" y="0.312388" z="-0.837364"/>
				<texcoord u="0.142446" v="0.416183"/>
			</vertex>
			<vertex>
				<position x="-0.0275549" y="-0.310187" z="-0.0387228"/>
				<normal x="-0.448593" y="0.312388" z="-0.837364"/>
				<texcoord u="0.142446" v="0.416183"/>
			</vertex>
			<vertex>
				<position x="-0.0037325" y="-0.421575" z="-0.141109"/>
				<normal x="0.00714522" y="0.472086" z="-0.881523"/>
				<texcoord u="0.267738" v="0.546036"/>
			</vertex>
			<vertex>
				<position x="-0.0787285" y="-0.446506" z="-0.0716158"/>
				<normal x="-0.949783" y="0.209363" z="-0.232552"/>
				<texcoord u="0.144428" v="0.587824"/>
			</vertex>
			<vertex>
				<position x="-0.115993" y="-0.819207" z="-0.0776441"/>
				<normal x="-0.770807" y="-0.637064" z="-0.00257524"/>
				<texcoord u="0.156454" v="0.981184"/>
			</vertex>
			<vertex>
				<position x="-0.0491411" y="-0.648708" z="0.0584578"/>
				<normal x="-0.536282" y="0.128326" z="0.834227"/>
				<texcoord u="0.016124" v="0.816589"/>
			</vertex>
			<vertex>
				<position x="-0.0473575" y="-0.480912" z="0.0195805"/>
				<normal x="-0.656021" y="-0.0683147" z="0.751644"/>
				<texcoord u="0.016124" v="0.609347"/>
			</vertex>
			<vertex>
				<position x="-0.0473575" y="-0.480912" z="0.0195805"/>
				<normal x="-0.656021" y="-0.0683147" z="0.751644"/>
				<texcoord u="0.016124" v="0.609347"/>
			</vertex>
			<vertex>
				<position x="-0.0787285" y="-0.446506" z="-0.0716158"/>
				<normal x="-0.949783" y="0.209363" z="-0.232552"/>
				<texcoord u="0.144428" v="0.587824"/>
			</vertex>
			<vertex>
				<position x="-0.115993" y="-0.819207" z="-0.0776441"/>
				<normal x="-0.770807" y="-0.637064" z="-0.00257524"/>
				<texcoord u="0.156454" v="0.981184"/>
			</vertex>
			<vertex>
				<position x="0.074935" y="-0.449712" z="-0.0694957"/>
				<normal x="0.95086" y="0.212898" z="-0.224809"/>
				<texcoord u="0.144428" v="0.587824"/>
			</vertex>
			<vertex>
				<position x="0.109295" y="-0.819927" z="-0.0754877"/>
				<normal x="0.77053" y="-0.637402" z="-0.00123026"/>
				<texcoord u="0.156454" v="0.981184"/>
			</vertex>
			<vertex>
				<position x="0.0570305" y="-0.791962" z="-0.221993"/>
				<normal x="0.474012" y="-0.444544" z="-0.760061"/>
				<texcoord u="0.317736" v="0.944003"/>
			</vertex>
			<vertex>
				<position x="-0.0676773" y="-0.791684" z="-0.222563"/>
				<normal x="-0.482345" y="-0.439791" z="-0.75758"/>
				<texcoord u="0.317736" v="0.944003"/>
			</vertex>
			<vertex>
				<position x="-0.115993" y="-0.819207" z="-0.0776441"/>
				<normal x="-0.770807" y="-0.637064" z="-0.00257524"/>
				<texcoord u="0.156454" v="0.981184"/>
			</vertex>
			<vertex>
				<position x="-0.0787285" y="-0.446506" z="-0.0716158"/>
				<normal x="-0.949783" y="0.209363" z="-0.232552"/>
				<texcoord u="0.144428" v="0.587824"/>
			</vertex>
			<vertex>
				<position x="0.043049" y="-0.290426" z="0.0869949"/>
				<normal x="0.691039" y="-0.278405" z="0.66705"/>
				<texcoord u="0.016124" v="0.377282"/>
			</vertex>
			<vertex>
				<position x="0.0330096" y="-0.355457" z="0.0874647"/>
				<normal x="0.489555" y="-0.234626" z="0.839813"/>
				<texcoord u="0.016124" v="0.46978"/>
			</vertex>
			<vertex>
				<position x="0.0633201" y="-0.329628" z="0.0182768"/>
				<normal x="0.997753" y="0.049405" z="-0.0452498"/>
				<texcoord u="0.0576082" v="0.441465"/>
			</vertex>
			<vertex>
				<position x="-0.0642376" y="-0.332824" z="0.0222099"/>
				<normal x="-0.99992" y="0.0114969" z="0.00525182"/>
				<texcoord u="0.0576082" v="0.441465"/>
			</vertex>
			<vertex>
				<position x="-0.0487441" y="-0.289542" z="0.0870624"/>
				<normal x="-0.679615" y="-0.300769" z="0.669075"/>
				<texcoord u="0.016124" v="0.377282"/>
			</vertex>
			<vertex>
				<position x="-0.0679783" y="-0.227175" z="-0.0221059"/>
				<normal x="-0.700581" y="-0.11783" z="-0.703777"/>
				<texcoord u="0.0950335" v="0.322154"/>
			</vertex>
			<vertex>
				<position x="-0.0642376" y="-0.332824" z="0.0222099"/>
				<normal x="-0.99992" y="0.0114969" z="0.00525182"/>
				<texcoord u="0.0576082" v="0.441465"/>
			</vertex>
			<vertex>
				<position x="-0.0442045" y="-0.354963" z="0.0862279"/>
				<normal x="-0.554023" y="-0.21911" z="0.80315"/>
				<texcoord u="0.016124" v="0.46978"/>
			</vertex>
			<vertex>
				<position x="-0.0487441" y="-0.289542" z="0.0870624"/>
				<normal x="-0.679615" y="-0.300769" z="0.669075"/>
				<texcoord u="0.016124" v="0.377282"/>
			</vertex>
			<vertex>
				<position x="-0.0759226" y="-0.030984" z="0.156507"/>
				<normal x="-0.640662" y="0.139876" z="0.754975"/>
				<texcoord u="0.722031" v="0.479194"/>
			</vertex>
			<vertex>
				<position x="-0.0699016" y="-0.177235" z="0.166817"/>
				<normal x="-0.597108" y="-0.240795" z="0.765167"/>
				<texcoord u="0.721424" v="0.386148"/>
			</vertex>
			<vertex>
				<position x="0.0627304" y="-0.176763" z="0.16468"/>
				<normal x="0.61977" y="-0.237191" z="0.748081"/>
				<texcoord u="0.551418" v="0.386217"/>
			</vertex>
			<vertex>
				<position x="0.0627304" y="-0.176763" z="0.16468"/>
				<normal x="0.61977" y="-0.237191" z="0.748081"/>
				<texcoord u="0.551418" v="0.386217"/>
			</vertex>
			<vertex>
				<position x="0.071519" y="-0.0249843" z="0.155756"/>
				<normal x="0.659358" y="0.1406" z="0.738566"/>
				<texcoord u="0.551271" v="0.483164"/>
			</vertex>
			<vertex>
				<position x="-0.0759226" y="-0.030984" z="0.156507"/>
				<normal x="-0.640662" y="0.139876" z="0.754975"/>
				<texcoord u="0.722031" v="0.479194"/>
			</vertex>
			<vertex>
				<position x="-0.00250727" y="0.36575" z="-0.0942797"/>
				<normal x="0.00166417" y="-0.198299" z="-0.98014"/>
				<texcoord u="0.491109" v="0.24109"/>
			</vertex>
			<vertex>
				<position x="-0.0722523" y="0.264689" z="-0.0360884"/>
				<normal x="-0.981095" y="-0.0850404" z="-0.17384"/>
				<texcoord u="0.343083" v="0.167526"/>
			</vertex>
			<vertex>
				<position x="-0.102504" y="0.660101" z="-0.0982915"/>
				<normal x="-0.854534" y="-0.211286" z="-0.474478"/>
				<texcoord u="0.767298" v="0.167526"/>
			</vertex>
			<vertex>
				<position x="-0.102504" y="0.660101" z="-0.0982915"/>
				<normal x="-0.854534" y="-0.211286" z="-0.474478"/>
				<texcoord u="0.767298" v="0.167526"/>
			</vertex>
			<vertex>
				<position x="-0.00250604" y="0.650644" z="-0.15664"/>
				<normal x="0.000539171" y="-0.260802" z="-0.965392"/>
				<texcoord u="0.767298" v="0.24109"/>
			</vertex>
			<vertex>
				<position x="-0.00250727" y="0.36575" z="-0.0942797"/>
				<normal x="0.00166417" y="-0.198299" z="-0.98014"/>
				<texcoord u="0.491109" v="0.24109"/>
			</vertex>
			<vertex>
				<position x="-0.102504" y="0.660101" z="-0.0982915"/>
				<normal x="-0.854534" y="-0.211286" z="-0.474478"/>
				<texcoord u="0.767298" v="0.167526"/>
			</vertex>
			<vertex>
				<position x="-0.0722523" y="0.264689" z="-0.0360884"/>
				<normal x="-0.981095" y="-0.0850404" z="-0.17384"/>
				<texcoord u="0.343083" v="0.167526"/>
			</vertex>
			<vertex>
				<position x="-0.0728463" y="0.275061" z="0.049006"/>
				<normal x="-0.878405" y="0.0223251" z="0.477395"/>
				<texcoord u="0.343083" v="0.0845604"/>
			</vertex>
			<vertex>
				<position x="-0.0728463" y="0.275061" z="0.049006"/>
				<normal x="-0.878405" y="0.0223251" z="0.477395"/>
				<texcoord u="0.343083" v="0.0845604"/>
			</vertex>
			<vertex>
				<position x="-0.102801" y="0.677552" z="0.00508246"/>
				<normal x="-0.832539" y="-0.0912095" z="0.546405"/>
				<texcoord u="0.767298" v="0.0845604"/>
			</vertex>
			<vertex>
				<position x="-0.102504" y="0.660101" z="-0.0982915"/>
				<normal x="-0.854534" y="-0.211286" z="-0.474478"/>
				<texcoord u="0.767298" v="0.167526"/>
			</vertex>
			<vertex>
				<position x="-0.00285787" y="0.282101" z="0.0939267"/>
				<normal x="-0.00729837" y="0.106462" z="0.99429"/>
				<texcoord u="0.343083" v="0.00538731"/>
			</vertex>
			<vertex>
				<position x="0.0672009" y="0.275061" z="0.049006"/>
				<normal x="0.880529" y="0.0182263" z="0.473642"/>
				<texcoord u="0.343083" v="0.0845604"/>
			</vertex>
			<vertex>
				<position x="0.0974738" y="0.677552" z="0.00508245"/>
				<normal x="0.836015" y="-0.082912" z="0.542407"/>
				<texcoord u="0.767298" v="0.0845604"/>
			</vertex>
			<vertex>
				<position x="0.0974738" y="0.677552" z="0.00508245"/>
				<normal x="0.836015" y="-0.082912" z="0.542407"/>
				<texcoord u="0.767298" v="0.0845604"/>
			</vertex>
			<vertex>
				<position x="-0.00195272" y="0.692634" z="0.0518426"/>
				<normal x="0.00241668" y="-0.00879112" z="0.999958"/>
				<texcoord u="0.783929" v="0.00538731"/>
			</vertex>
			<vertex>
				<position x="-0.00285787" y="0.282101" z="0.0939267"/>
				<normal x="-0.00729837" y="0.106462" z="0.99429"/>
				<texcoord u="0.343083" v="0.00538731"/>
			</vertex>
			<vertex>
				<position x="0.0672009" y="0.275061" z="0.049006"/>
				<normal x="0.880529" y="0.0182263" z="0.473642"/>
				<texcoord u="0.343083" v="0.0845604"/>
			</vertex>
			<vertex>
				<position x="0.0666086" y="0.26474" z="-0.036098"/>
				<normal x="0.981646" y="-0.0801312" z="-0.173061"/>
				<texcoord u="0.343083" v="0.167526"/>
			</vertex>
			<vertex>
				<position x="0.0971776" y="0.660101" z="-0.098292"/>
				<normal x="0.854777" y="-0.212136" z="-0.473661"/>
				<texcoord u="0.767298" v="0.167526"/>
			</vertex>
			<vertex>
				<position x="0.0971776" y="0.660101" z="-0.098292"/>
				<normal x="0.854777" y="-0.212136" z="-0.473661"/>
				<texcoord u="0.767298" v="0.167526"/>
			</vertex>
			<vertex>
				<position x="0.0974738" y="0.677552" z="0.00508245"/>
				<normal x="0.836015" y="-0.082912" z="0.542407"/>
				<texcoord u="0.767298" v="0.0845604"/>
			</vertex>
			<vertex>
				<position x="0.0672009" y="0.275061" z="0.049006"/>
				<normal x="0.880529" y="0.0182263" z="0.473642"/>
				<texcoord u="0.343083" v="0.0845604"/>
			</vertex>
			<vertex>
				<position x="0.0971776" y="0.660101" z="-0.098292"/>
				<normal x="0.854777" y="-0.212136" z="-0.473661"/>
				<texcoord u="0.767298" v="0.167526"/>
			</vertex>
			<vertex>
				<position x="0.0666086" y="0.26474" z="-0.036098"/>
				<normal x="0.981646" y="-0.0801312" z="-0.173061"/>
				<texcoord u="0.343083" v="0.167526"/>
			</vertex>
			<vertex>
				<position x="-0.00250727" y="0.36575" z="-0.0942797"/>
				<normal x="0.00166417" y="-0.198299" z="-0.98014"/>
				<texcoord u="0.491109" v="0.24109"/>
			</vertex>
			<vertex>
				<position x="-0.00250727" y="0.36575" z="-0.0942797"/>
				<normal x="0.00166417" y="-0.198299" z="-0.98014"/>
				<texcoord u="0.491109" v="0.24109"/>
			</vertex>
			<vertex>
				<position x="-0.00250604" y="0.650644" z="-0.15664"/>
				<normal x="0.000539171" y="-0.260802" z="-0.965392"/>
				<texcoord u="0.767298" v="0.24109"/>
			</vertex>
			<vertex>
				<position x="0.0971776" y="0.660101" z="-0.098292"/>
				<normal x="0.854777" y="-0.212136" z="-0.473661"/>
				<texcoord u="0.767298" v="0.167526"/>
			</vertex>
			<vertex>
				<position x="-0.0728463" y="0.275061" z="0.049006"/>
				<normal x="-0.878405" y="0.0223251" z="0.477395"/>
				<texcoord u="0.343083" v="0.0845604"/>
			</vertex>
			<vertex>
				<position x="-0.00285787" y="0.282101" z="0.0939267"/>
				<normal x="-0.00729837" y="0.106462" z="0.99429"/>
				<texcoord u="0.343083" v="0.00538731"/>
			</vertex>
			<vertex>
				<position x="-0.00195272" y="0.692634" z="0.0518426"/>
				<normal x="0.00241668" y="-0.00879112" z="0.999958"/>
				<texcoord u="0.783929" v="0.00538731"/>
			</vertex>
			<vertex>
				<position x="-0.00195272" y="0.692634" z="0.0518426"/>
				<normal x="0.00241668" y="-0.00879112" z="0.999958"/>
				<texcoord u="0.783929" v="0.00538731"/>
			</vertex>
			<vertex>
				<position x="-0.102801" y="0.677552" z="0.00508246"/>
				<normal x="-0.832539" y="-0.0912095" z="0.546405"/>
				<texcoord u="0.767298" v="0.0845604"/>
			</vertex>
			<vertex>
				<position x="-0.0728463" y="0.275061" z="0.049006"/>
				<normal x="-0.878405" y="0.0223251" z="0.477395"/>
				<texcoord u="0.343083" v="0.0845604"/>
			</vertex>
			<vertex>
				<position x="0.0398403" y="-0.649002" z="0.0577472"/>
				<normal x="0.52935" y="0.121825" z="0.839611"/>
				<texcoord u="0.016124" v="0.816589"/>
			</vertex>
			<vertex>
				<position x="0.0403442" y="-0.480085" z="0.0200231"/>
				<normal x="0.638015" y="-0.0824735" z="0.765594"/>
				<texcoord u="0.016124" v="0.609347"/>
			</vertex>
			<vertex>
				<position x="-0.0473575" y="-0.480912" z="0.0195805"/>
				<normal x="-0.656021" y="-0.0683147" z="0.751644"/>
				<texcoord u="0.016124" v="0.609347"/>
			</vertex>
			<vertex>
				<position x="-0.0473575" y="-0.480912" z="0.0195805"/>
				<normal x="-0.656021" y="-0.0683147" z="0.751644"/>
				<texcoord u="0.016124" v="0.609347"/>
			</vertex>
			<vertex>
				<position x="-0.0491411" y="-0.648708" z="0.0584578"/>
				<normal x="-0.536282" y="0.128326" z="0.834227"/>
				<texcoord u="0.016124" v="0.816589"/>
			</vertex>
			<vertex>
				<position x="0.0398403" y="-0.649002" z="0.0577472"/>
				<normal x="0.52935" y="0.121825" z="0.839611"/>
				<texcoord u="0.016124" v="0.816589"/>
			</vertex>
			<vertex>
				<position x="0.109295" y="-0.819927" z="-0.0754877"/>
				<normal x="0.77053" y="-0.637402" z="-0.00123026"/>
				<texcoord u="0.156454" v="0.981184"/>
			</vertex>
			<vertex>
				<position x="0.074935" y="-0.449712" z="-0.0694957"/>
				<normal x="0.95086" y="0.212898" z="-0.224809"/>
				<texcoord u="0.144428" v="0.587824"/>
			</vertex>
			<vertex>
				<position x="0.0403442" y="-0.480085" z="0.0200231"/>
				<normal x="0.638015" y="-0.0824735" z="0.765594"/>
				<texcoord u="0.016124" v="0.609347"/>
			</vertex>
			<vertex>
				<position x="0.0403442" y="-0.480085" z="0.0200231"/>
				<normal x="0.638015" y="-0.0824735" z="0.765594"/>
				<texcoord u="0.016124" v="0.609347"/>
			</vertex>
			<vertex>
				<position x="0.0398403" y="-0.649002" z="0.0577472"/>
				<normal x="0.52935" y="0.121825" z="0.839611"/>
				<texcoord u="0.016124" v="0.816589"/>
			</vertex>
			<vertex>
				<position x="0.109295" y="-0.819927" z="-0.0754877"/>
				<normal x="0.77053" y="-0.637402" z="-0.00123026"/>
				<texcoord u="0.156454" v="0.981184"/>
			</vertex>
			<vertex>
				<position x="-0.115993" y="-0.819207" z="-0.0776441"/>
				<normal x="-0.770807" y="-0.637064" z="-0.00257524"/>
				<texcoord u="0.156454" v="0.981184"/>
			</vertex>
			<vertex>
				<position x="-0.0632587" y="-0.801396" z="0.0621366"/>
				<normal x="-0.478709" y="-0.519743" z="0.707605"/>
				<texcoord u="0.016124" v="0.981184"/>
			</vertex>
			<vertex>
				<position x="-0.0491411" y="-0.648708" z="0.0584578"/>
				<normal x="-0.536282" y="0.128326" z="0.834227"/>
				<texcoord u="0.016124" v="0.816589"/>
			</vertex>
			<vertex>
				<position x="0.0537258" y="-0.227231" z="-0.0199611"/>
				<normal x="0.682228" y="-0.0972174" z="-0.724648"/>
				<texcoord u="0.0950335" v="0.322154"/>
			</vertex>
			<vertex>
				<position x="0.0633201" y="-0.329628" z="0.0182768"/>
				<normal x="0.997753" y="0.049405" z="-0.0452498"/>
				<texcoord u="0.0576082" v="0.441465"/>
			</vertex>
			<vertex>
				<position x="0.0124707" y="-0.313014" z="-0.0366683"/>
				<normal x="0.43577" y="0.336406" z="-0.834827"/>
				<texcoord u="0.142446" v="0.416183"/>
			</vertex>
			<vertex>
				<position x="0.0124707" y="-0.313014" z="-0.0366683"/>
				<normal x="0.43577" y="0.336406" z="-0.834827"/>
				<texcoord u="0.142446" v="0.416183"/>
			</vertex>
			<vertex>
				<position x="0.0633201" y="-0.329628" z="0.0182768"/>
				<normal x="0.997753" y="0.049405" z="-0.0452498"/>
				<texcoord u="0.0576082" v="0.441465"/>
			</vertex>
			<vertex>
				<position x="0.074935" y="-0.449712" z="-0.0694957"/>
				<normal x="0.95086" y="0.212898" z="-0.224809"/>
				<texcoord u="0.144428" v="0.587824"/>
			</vertex>
			<vertex>
				<position x="0.074935" y="-0.449712" z="-0.0694957"/>
				<normal x="0.95086" y="0.212898" z="-0.224809"/>
				<texcoord u="0.144428" v="0.587824"/>
			</vertex>
			<vertex>
				<position x="-0.0037325" y="-0.421575" z="-0.141109"/>
				<normal x="0.00714522" y="0.472086" z="-0.881523"/>
				<texcoord u="0.267738" v="0.546036"/>
			</vertex>
			<vertex>
				<position x="0.0124707" y="-0.313014" z="-0.0366683"/>
				<normal x="0.43577" y="0.336406" z="-0.834827"/>
				<texcoord u="0.142446" v="0.416183"/>
			</vertex>
			<vertex>
				<position x="-0.0275549" y="-0.310187" z="-0.0387228"/>
				<normal x="-0.448593" y="0.312388" z="-0.837364"/>
				<texcoord u="0.142446" v="0.416183"/>
			</vertex>
			<vertex>
				<position x="-0.00373259" y="-0.311601" z="-0.0376956"/>
				<normal x="0.0806883" y="0.45424" z="-0.887218"/>
				<texcoord u="0.189523" v="0.409772"/>
			</vertex>
			<vertex>
				<position x="-0.0037325" y="-0.421575" z="-0.141109"/>
				<normal x="0.00714522" y="0.472086" z="-0.881523"/>
				<texcoord u="0.267738" v="0.546036"/>
			</vertex>
			<vertex>
				<position x="-0.0679783" y="-0.227175" z="-0.0221059"/>
				<normal x="-0.700581" y="-0.11783" z="-0.703777"/>
				<texcoord u="0.56079" v="0.774727"/>
			</vertex>
			<vertex>
				<position x="-0.0844387" y="-0.0151036" z="-0.0420298"/>
				<normal x="-0.793669" y="-0.231264" z="-0.562679"/>
				<texcoord u="0.56079" v="0.977362"/>
			</vertex>
			<vertex>
				<position x="-0.00373257" y="-0.0161498" z="-0.0414431"/>
				<normal x="-0.00475936" y="-0.806174" z="-0.591659"/>
				<texcoord u="0.638669" v="0.977362"/>
			</vertex>
			<vertex>
				<position x="-0.00373257" y="-0.0161498" z="-0.0414431"/>
				<normal x="-0.00475936" y="-0.806174" z="-0.591659"/>
				<texcoord u="0.638669" v="0.977362"/>
			</vertex>
			<vertex>
				<position x="-0.00373259" y="-0.227203" z="-0.0210335"/>
				<normal x="0.0211148" y="0.0488842" z="-0.998581"/>
				<texcoord u="0.638669" v="0.774727"/>
			</vertex>
			<vertex>
				<position x="-0.0679783" y="-0.227175" z="-0.0221059"/>
				<normal x="-0.700581" y="-0.11783" z="-0.703777"/>
				<texcoord u="0.56079" v="0.774727"/>
			</vertex>
			<vertex>
				<position x="-0.00373259" y="-0.227203" z="-0.0210335"/>
				<normal x="0.0211148" y="0.0488842" z="-0.998581"/>
				<texcoord u="0.189523" v="0.322154"/>
			</vertex>
			<vertex>
				<position x="0.0537258" y="-0.227231" z="-0.0199611"/>
				<normal x="0.682228" y="-0.0972174" z="-0.724648"/>
				<texcoord u="0.0950335" v="0.322154"/>
			</vertex>
			<vertex>
				<position x="0.0124707" y="-0.313014" z="-0.0366683"/>
				<normal x="0.43577" y="0.336406" z="-0.834827"/>
				<texcoord u="0.142446" v="0.416183"/>
			</vertex>
			<vertex>
				<position x="0.0124707" y="-0.313014" z="-0.0366683"/>
				<normal x="0.43577" y="0.336406" z="-0.834827"/>
				<texcoord u="0.142446" v="0.416183"/>
			</vertex>
			<vertex>
				<position x="-0.00373259" y="-0.311601" z="-0.0376956"/>
				<normal x="0.0806883" y="0.45424" z="-0.887218"/>
				<texcoord u="0.189523" v="0.409772"/>
			</vertex>
			<vertex>
				<position x="-0.00373259" y="-0.227203" z="-0.0210335"/>
				<normal x="0.0211148" y="0.0488842" z="-0.998581"/>
				<texcoord u="0.189523" v="0.322154"/>
			</vertex>
			<vertex>
				<position x="-0.00373259" y="-0.311601" z="-0.0376956"/>
				<normal x="0.0806883" y="0.45424" z="-0.887218"/>
				<texcoord u="0.189523" v="0.409772"/>
			</vertex>
			<vertex>
				<position x="0.0124707" y="-0.313014" z="-0.0366683"/>
				<normal x="0.43577" y="0.336406" z="-0.834827"/>
				<texcoord u="0.142446" v="0.416183"/>
			</vertex>
			<vertex>
				<position x="-0.0037325" y="-0.421575" z="-0.141109"/>
				<normal x="0.00714522" y="0.472086" z="-0.881523"/>
				<texcoord u="0.267738" v="0.546036"/>
			</vertex>
			<vertex>
				<position x="-0.00373255" y="-0.0284471" z="-0.09974"/>
				<normal x="0.00707185" y="-0.740842" z="-0.671643"/>
				<texcoord u="0.51655" v="0.851527"/>
			</vertex>
			<vertex>
				<position x="0.073739" y="-0.017196" z="-0.0408564"/>
				<normal x="0.806373" y="-0.225634" z="-0.546673"/>
				<texcoord u="0.412165" v="0.762513"/>
			</vertex>
			<vertex>
				<position x="-0.00373257" y="-0.0161498" z="-0.0414431"/>
				<normal x="-0.00475936" y="-0.806174" z="-0.591659"/>
				<texcoord u="0.46304" v="0.866961"/>
			</vertex>
			<vertex>
				<position x="0.0776454" y="-0.00828766" z="0.0219938"/>
				<normal x="0.999288" y="-0.0354372" z="-0.0129603"/>
				<texcoord u="0.819446" v="0.247971"/>
			</vertex>
			<vertex>
				<position x="0.0733755" y="0.00523522" z="0.142969"/>
				<normal x="0.763912" y="0.208264" z="0.61079"/>
				<texcoord u="0.984355" v="0.248047"/>
			</vertex>
			<vertex>
				<position x="0.071519" y="-0.0249843" z="0.155756"/>
				<normal x="0.659358" y="0.1406" z="0.738566"/>
				<texcoord u="0.984355" v="0.292055"/>
			</vertex>
			<vertex>
				<position x="0.0733755" y="0.00523522" z="0.142969"/>
				<normal x="0.763912" y="0.208264" z="0.61079"/>
				<texcoord u="0.551012" v="0.496514"/>
			</vertex>
			<vertex>
				<position x="-0.0774943" y="0.00525699" z="0.142349"/>
				<normal x="-0.729655" y="0.221134" z="0.647073"/>
				<texcoord u="0.721977" v="0.496556"/>
			</vertex>
			<vertex>
				<position x="-0.0759226" y="-0.030984" z="0.156507"/>
				<normal x="-0.640662" y="0.139876" z="0.754975"/>
				<texcoord u="0.722031" v="0.479194"/>
			</vertex>
			<vertex>
				<position x="-0.0759226" y="-0.030984" z="0.156507"/>
				<normal x="-0.640662" y="0.139876" z="0.754975"/>
				<texcoord u="0.722031" v="0.479194"/>
			</vertex>
			<vertex>
				<position x="0.071519" y="-0.0249843" z="0.155756"/>
				<normal x="0.659358" y="0.1406" z="0.738566"/>
				<texcoord u="0.551271" v="0.483164"/>
			</vertex>
			<vertex>
				<position x="0.0733755" y="0.00523522" z="0.142969"/>
				<normal x="0.763912" y="0.208264" z="0.61079"/>
				<texcoord u="0.551012" v="0.496514"/>
			</vertex>
			<vertex>
				<position x="-0.0759226" y="-0.030984" z="0.156507"/>
				<normal x="-0.640662" y="0.139876" z="0.754975"/>
				<texcoord u="0.984355" v="0.292055"/>
			</vertex>
			<vertex>
				<position x="-0.0774943" y="0.00525699" z="0.142349"/>
				<normal x="-0.729655" y="0.221134" z="0.647073"/>
				<texcoord u="0.984355" v="0.248047"/>
			</vertex>
			<vertex>
				<position x="-0.0903458" y="-0.00869397" z="0.022208"/>
				<normal x="-0.99904" y="-0.041812" z="-0.0130468"/>
				<texcoord u="0.819446" v="0.247971"/>
			</vertex>
			<vertex>
				<position x="-0.0037325" y="-0.421575" z="-0.141109"/>
				<normal x="0.00714522" y="0.472086" z="-0.881523"/>
				<texcoord u="0.267738" v="0.546036"/>
			</vertex>
			<vertex>
				<position x="0.074935" y="-0.449712" z="-0.0694957"/>
				<normal x="0.95086" y="0.212898" z="-0.224809"/>
				<texcoord u="0.144428" v="0.587824"/>
			</vertex>
			<vertex>
				<position x="0.0570305" y="-0.791962" z="-0.221993"/>
				<normal x="0.474012" y="-0.444544" z="-0.760061"/>
				<texcoord u="0.317736" v="0.944003"/>
			</vertex>
			<vertex>
				<position x="-0.0037325" y="-0.421575" z="-0.141109"/>
				<normal x="0.00714522" y="0.472086" z="-0.881523"/>
				<texcoord u="0.267738" v="0.546036"/>
			</vertex>
			<vertex>
				<position x="0.0570305" y="-0.791962" z="-0.221993"/>
				<normal x="0.474012" y="-0.444544" z="-0.760061"/>
				<texcoord u="0.317736" v="0.944003"/>
			</vertex>
			<vertex>
				<position x="-0.0676773" y="-0.791684" z="-0.222563"/>
				<normal x="-0.482345" y="-0.439791" z="-0.75758"/>
				<texcoord u="0.357531" v="0.794582"/>
			</vertex>
			<vertex>
				<position x="-0.00993221" y="-0.012177" z="-0.0434984"/>
				<normal x="0.999902" y="-0.00410756" z="0.0133669"/>
				<texcoord u="0.361447" v="0.439393"/>
			</vertex>
			<vertex>
				<position x="-0.0128478" y="-0.317139" z="0.0051349"/>
				<normal x="0.999756" y="-0.00617678" z="0.0212025"/>
				<texcoord u="0.361447" v="0.197269"/>
			</vertex>
			<vertex>
				<position x="-0.0101205" y="-0.338188" z="-0.129594"/>
				<normal x="0.999815" y="-0.00544968" z="0.0184492"/>
				<texcoord u="0.242541" v="0.197269"/>
			</vertex>
			<vertex>
				<position x="-0.0101205" y="-0.338188" z="-0.129594"/>
				<normal x="0.999815" y="-0.00544968" z="0.0184492"/>
				<texcoord u="0.242541" v="0.197269"/>
			</vertex>
			<vertex>
				<position x="-0.00868335" y="-0.0384041" z="-0.17162"/>
				<normal x="0.99994" y="-0.00333172" z="0.0104289"/>
				<texcoord u="0.242541" v="0.439393"/>
			</vertex>
			<vertex>
				<position x="-0.00993221" y="-0.012177" z="-0.0434984"/>
				<normal x="0.999902" y="-0.00410756" z="0.0133669"/>
				<texcoord u="0.361447" v="0.439393"/>
			</vertex>
			<vertex>
				<position x="0.0693617" y="-0.0642567" z="0.254741"/>
				<normal x="0.987271" y="-0.112076" z="0.112852"/>
				<texcoord u="0.532849" v="0.285226"/>
			</vertex>
			<vertex>
				<position x="0.0533732" y="-0.166318" z="0.269094"/>
				<normal x="0.981621" y="-0.134775" z="0.135112"/>
				<texcoord u="0.384049" v="0.285226"/>
			</vertex>
			<vertex>
				<position x="0.0697279" y="-0.188402" z="0.128245"/>
				<normal x="0.989863" y="-0.0999227" z="0.100932"/>
				<texcoord u="0.384049" v="0.431933"/>
			</vertex>
			<vertex>
				<position x="0.0697279" y="-0.188402" z="0.128245"/>
				<normal x="0.989863" y="-0.0999227" z="0.100932"/>
				<texcoord u="0.384049" v="0.431933"/>
			</vertex>
			<vertex>
				<position x="0.0776092" y="-0.0915179" z="0.120498"/>
				<normal x="0.994279" y="-0.0747836" z="0.0762725"/>
				<texcoord u="0.532849" v="0.431933"/>
			</vertex>
			<vertex>
				<position x="0.0693617" y="-0.0642567" z="0.254741"/>
				<normal x="0.987271" y="-0.112076" z="0.112852"/>
				<texcoord u="0.532849" v="0.285226"/>
			</vertex>
			<vertex>
				<position x="0.0762536" y="0.0336246" z="0.223588"/>
				<normal x="0.989696" y="-0.0854838" z="0.114867"/>
				<texcoord u="0.298527" v="0.451838"/>
			</vertex>
			<vertex>
				<position x="0.0641556" y="-0.0514196" z="0.249682"/>
				<normal x="0.986742" y="-0.101514" z="0.126633"/>
				<texcoord u="0.298527" v="0.579669"/>
			</vertex>
			<vertex>
				<position x="0.0853859" y="-0.0973577" z="0.0474265"/>
				<normal x="0.994598" y="-0.0517093" z="0.0900082"/>
				<texcoord u="0.524618" v="0.579669"/>
			</vertex>
			<vertex>
				<position x="0.0853859" y="-0.0973577" z="0.0474265"/>
				<normal x="0.994598" y="-0.0517093" z="0.0900082"/>
				<texcoord u="0.524618" v="0.579669"/>
			</vertex>
			<vertex>
				<position x="0.0893766" y="-0.0170621" z="0.03048"/>
				<normal x="0.996512" y="-0.0333849" z="0.0764825"/>
				<texcoord u="0.531229" v="0.451838"/>
			</vertex>
			<vertex>
				<position x="0.0762536" y="0.0336246" z="0.223588"/>
				<normal x="0.989696" y="-0.0854838" z="0.114867"/>
				<texcoord u="0.298527" v="0.451838"/>
			</vertex>
			<vertex>
				<position x="-0.0120854" y="-0.012177" z="-0.0434984"/>
				<normal x="-0.999902" y="0.00410757" z="-0.0133669"/>
				<texcoord u="0.361447" v="0.439393"/>
			</vertex>
			<vertex>
				<position x="-0.0108365" y="-0.0384041" z="-0.17162"/>
				<normal x="-0.99994" y="0.00333172" z="-0.0104289"/>
				<texcoord u="0.242541" v="0.439393"/>
			</vertex>
			<vertex>
				<position x="-0.0122737" y="-0.338188" z="-0.129594"/>
				<normal x="-0.999815" y="0.00544969" z="-0.0184492"/>
				<texcoord u="0.242541" v="0.197269"/>
			</vertex>
			<vertex>
				<position x="-0.0122737" y="-0.338188" z="-0.129594"/>
				<normal x="-0.999815" y="0.00544969" z="-0.0184492"/>
				<texcoord u="0.242541" v="0.197269"/>
			</vertex>
			<vertex>
				<position x="-0.0150009" y="-0.317139" z="0.0051349"/>
				<normal x="-0.999756" y="0.00617678" z="-0.0212025"/>
				<texcoord u="0.361447" v="0.197269"/>
			</vertex>
			<vertex>
				<position x="-0.0120854" y="-0.012177" z="-0.0434984"/>
				<normal x="-0.999902" y="0.00410757" z="-0.0133669"/>
				<texcoord u="0.361447" v="0.439393"/>
			</vertex>
			<vertex>
				<position x="0.0672085" y="-0.0642567" z="0.254741"/>
				<normal x="-0.987271" y="0.112076" z="-0.112852"/>
				<texcoord u="0.532849" v="0.285226"/>
			</vertex>
			<vertex>
				<position x="0.075456" y="-0.0915179" z="0.120498"/>
				<normal x="-0.994279" y="0.0747836" z="-0.0762725"/>
				<texcoord u="0.532849" v="0.431933"/>
			</vertex>
			<vertex>
				<position x="0.0675748" y="-0.188402" z="0.128245"/>
				<normal x="-0.989863" y="0.0999227" z="-0.100932"/>
				<texcoord u="0.384049" v="0.431933"/>
			</vertex>
			<vertex>
				<position x="0.0675748" y="-0.188402" z="0.128245"/>
				<normal x="-0.989863" y="0.0999227" z="-0.100932"/>
				<texcoord u="0.384049" v="0.431933"/>
			</vertex>
			<vertex>
				<position x="0.05122" y="-0.166318" z="0.269094"/>
				<normal x="-0.981621" y="0.134775" z="-0.135112"/>
				<texcoord u="0.384049" v="0.285226"/>
			</vertex>
			<vertex>
				<position x="0.0672085" y="-0.0642567" z="0.254741"/>
				<normal x="-0.987271" y="0.112076" z="-0.112852"/>
				<texcoord u="0.532849" v="0.285226"/>
			</vertex>
			<vertex>
				<position x="0.0741004" y="0.0336246" z="0.223588"/>
				<normal x="-0.989696" y="0.0854838" z="-0.114867"/>
				<texcoord u="0.298527" v="0.451838"/>
			</vertex>
			<vertex>
				<position x="0.0872234" y="-0.0170621" z="0.03048"/>
				<normal x="-0.996512" y="0.0333847" z="-0.0764825"/>
				<texcoord u="0.531229" v="0.451838"/>
			</vertex>
			<vertex>
				<position x="0.0832327" y="-0.0973577" z="0.0474265"/>
				<normal x="-0.994598" y="0.0517092" z="-0.0900081"/>
				<texcoord u="0.524618" v="0.579669"/>
			</vertex>
			<vertex>
				<position x="0.0832327" y="-0.0973577" z="0.0474265"/>
				<normal x="-0.994598" y="0.0517092" z="-0.0900081"/>
				<texcoord u="0.524618" v="0.579669"/>
			</vertex>
			<vertex>
				<position x="0.0620024" y="-0.0514196" z="0.249682"/>
				<normal x="-0.986742" y="0.101514" z="-0.126633"/>
				<texcoord u="0.298527" v="0.579669"/>
			</vertex>
			<vertex>
				<position x="0.0741004" y="0.0336246" z="0.223588"/>
				<normal x="-0.989696" y="0.0854838" z="-0.114867"/>
				<texcoord u="0.298527" v="0.451838"/>
			</vertex>
		</vertexbuffer>
	</sharedgeometry>
	<submeshes>
		<submesh material="rifle_02_02" usesharedvertices="true" use32bitindexes="false">
			<faces count="156">
				<face v1="0" v2="1" v3="2"/>
				<face v1="3" v2="4" v3="5"/>
				<face v1="6" v2="7" v3="8"/>
				<face v1="9" v2="10" v3="11"/>
				<face v1="12" v2="13" v3="14"/>
				<face v1="15" v2="16" v3="17"/>
				<face v1="18" v2="19" v3="20"/>
				<face v1="21" v2="22" v3="23"/>
				<face v1="24" v2="25" v3="26"/>
				<face v1="27" v2="28" v3="29"/>
				<face v1="30" v2="31" v3="32"/>
				<face v1="33" v2="34" v3="35"/>
				<face v1="36" v2="37" v3="38"/>
				<face v1="39" v2="40" v3="41"/>
				<face v1="42" v2="43" v3="44"/>
				<face v1="45" v2="46" v3="47"/>
				<face v1="48" v2="49" v3="50"/>
				<face v1="51" v2="52" v3="53"/>
				<face v1="54" v2="55" v3="56"/>
				<face v1="57" v2="58" v3="59"/>
				<face v1="60" v2="61" v3="62"/>
				<face v1="63" v2="64" v3="65"/>
				<face v1="66" v2="67" v3="68"/>
				<face v1="69" v2="70" v3="71"/>
				<face v1="72" v2="73" v3="74"/>
				<face v1="75" v2="76" v3="77"/>
				<face v1="78" v2="79" v3="80"/>
				<face v1="81" v2="82" v3="83"/>
				<face v1="84" v2="85" v3="86"/>
				<face v1="87" v2="88" v3="89"/>
				<face v1="90" v2="91" v3="92"/>
				<face v1="93" v2="94" v3="95"/>
				<face v1="96" v2="97" v3="98"/>
				<face v1="99" v2="100" v3="101"/>
				<face v1="102" v2="103" v3="104"/>
				<face v1="105" v2="106" v3="107"/>
				<face v1="108" v2="109" v3="110"/>
				<face v1="111" v2="112" v3="113"/>
				<face v1="114" v2="115" v3="116"/>
				<face v1="117" v2="118" v3="119"/>
				<face v1="120" v2="121" v3="122"/>
				<face v1="123" v2="124" v3="125"/>
				<face v1="126" v2="127" v3="128"/>
				<face v1="129" v2="130" v3="131"/>
				<face v1="132" v2="133" v3="134"/>
				<face v1="135" v2="136" v3="137"/>
				<face v1="138" v2="139" v3="140"/>
				<face v1="141" v2="142" v3="143"/>
				<face v1="144" v2="145" v3="146"/>
				<face v1="147" v2="148" v3="149"/>
				<face v1="150" v2="151" v3="152"/>
				<face v1="153" v2="154" v3="155"/>
				<face v1="156" v2="157" v3="158"/>
				<face v1="159" v2="160" v3="161"/>
				<face v1="162" v2="163" v3="164"/>
				<face v1="165" v2="166" v3="167"/>
				<face v1="168" v2="169" v3="170"/>
				<face v1="171" v2="172" v3="173"/>
				<face v1="174" v2="175" v3="176"/>
				<face v1="177" v2="178" v3="179"/>
				<face v1="180" v2="181" v3="182"/>
				<face v1="183" v2="184" v3="185"/>
				<face v1="186" v2="187" v3="188"/>
				<face v1="189" v2="190" v3="191"/>
				<face v1="192" v2="193" v3="194"/>
				<face v1="195" v2="196" v3="197"/>
				<face v1="198" v2="199" v3="200"/>
				<face v1="201" v2="202" v3="203"/>
				<face v1="204" v2="205" v3="206"/>
				<face v1="207" v2="208" v3="209"/>
				<face v1="210" v2="211" v3="212"/>
				<face v1="213" v2="214" v3="215"/>
				<face v1="216" v2="217" v3="218"/>
				<face v1="219" v2="220" v3="221"/>
				<face v1="222" v2="223" v3="224"/>
				<face v1="225" v2="226" v3="227"/>
				<face v1="228" v2="229" v3="230"/>
				<face v1="231" v2="232" v3="233"/>
				<face v1="234" v2="235" v3="236"/>
				<face v1="237" v2="238" v3="239"/>
				<face v1="240" v2="241" v3="242"/>
				<face v1="243" v2="244" v3="245"/>
				<face v1="246" v2="247" v3="248"/>
				<face v1="249" v2="250" v3="251"/>
				<face v1="252" v2="253" v3="254"/>
				<face v1="255" v2="256" v3="257"/>
				<face v1="258" v2="259" v3="260"/>
				<face v1="261" v2="262" v3="263"/>
				<face v1="264" v2="265" v3="266"/>
				<face v1="267" v2="268" v3="269"/>
				<face v1="270" v2="271" v3="272"/>
				<face v1="273" v2="274" v3="275"/>
				<face v1="276" v2="277" v3="278"/>
				<face v1="279" v2="280" v3="281"/>
				<face v1="282" v2="283" v3="284"/>
				<face v1="285" v2="286" v3="287"/>
				<face v1="288" v2="289" v3="290"/>
				<face v1="291" v2="292" v3="293"/>
				<face v1="294" v2="295" v3="296"/>
				<face v1="297" v2="298" v3="299"/>
				<face v1="300" v2="301" v3="302"/>
				<face v1="303" v2="304" v3="305"/>
				<face v1="306" v2="307" v3="308"/>
				<face v1="309" v2="310" v3="311"/>
				<face v1="312" v2="313" v3="314"/>
				<face v1="315" v2="316" v3="317"/>
				<face v1="318" v2="319" v3="320"/>
				<face v1="321" v2="322" v3="323"/>
				<face v1="324" v2="325" v3="326"/>
				<face v1="327" v2="328" v3="329"/>
				<face v1="330" v2="331" v3="332"/>
				<face v1="333" v2="334" v3="335"/>
				<face v1="336" v2="337" v3="338"/>
				<face v1="339" v2="340" v3="341"/>
				<face v1="342" v2="343" v3="344"/>
				<face v1="345" v2="346" v3="347"/>
				<face v1="348" v2="349" v3="350"/>
				<face v1="351" v2="352" v3="353"/>
				<face v1="354" v2="355" v3="356"/>
				<face v1="357" v2="358" v3="359"/>
				<face v1="360" v2="361" v3="362"/>
				<face v1="363" v2="364" v3="365"/>
				<face v1="366" v2="367" v3="368"/>
				<face v1="369" v2="370" v3="371"/>
				<face v1="372" v2="373" v3="374"/>
				<face v1="375" v2="376" v3="377"/>
				<face v1="378" v2="379" v3="380"/>
				<face v1="381" v2="382" v3="383"/>
				<face v1="384" v2="385" v3="386"/>
				<face v1="387" v2="388" v3="389"/>
				<face v1="390" v2="391" v3="392"/>
				<face v1="393" v2="394" v3="395"/>
				<face v1="396" v2="397" v3="398"/>
				<face v1="399" v2="400" v3="401"/>
				<face v1="402" v2="403" v3="404"/>
				<face v1="405" v2="406" v3="407"/>
				<face v1="408" v2="409" v3="410"/>
				<face v1="411" v2="412" v3="413"/>
				<face v1="414" v2="415" v3="416"/>
				<face v1="417" v2="418" v3="419"/>
				<face v1="420" v2="421" v3="422"/>
				<face v1="423" v2="424" v3="425"/>
				<face v1="426" v2="427" v3="428"/>
				<face v1="429" v2="430" v3="431"/>
				<face v1="432" v2="433" v3="434"/>
				<face v1="435" v2="436" v3="437"/>
				<face v1="438" v2="439" v3="440"/>
				<face v1="441" v2="442" v3="443"/>
				<face v1="444" v2="445" v3="446"/>
				<face v1="447" v2="448" v3="449"/>
				<face v1="450" v2="451" v3="452"/>
				<face v1="453" v2="454" v3="455"/>
				<face v1="456" v2="457" v3="458"/>
				<face v1="459" v2="460" v3="461"/>
				<face v1="462" v2="463" v3="464"/>
				<face v1="465" v2="466" v3="467"/>
			</faces>
		</submesh>
	</submeshes>
</mesh>
